{"hierarchy":{"paths":[["doc:\/\/Afluent\/documentation\/Afluent","doc:\/\/Afluent\/documentation\/Afluent\/AsyncSequences","doc:\/\/Afluent\/documentation\/Afluent\/AsyncSequences\/RetryAfterFlatMapping"]]},"topicSections":[{"title":"Instance Properties","identifiers":["doc:\/\/Afluent\/documentation\/Afluent\/AsyncSequences\/RetryAfterFlatMapping\/characters","doc:\/\/Afluent\/documentation\/Afluent\/AsyncSequences\/RetryAfterFlatMapping\/lines","doc:\/\/Afluent\/documentation\/Afluent\/AsyncSequences\/RetryAfterFlatMapping\/unicodeScalars"],"generated":true},{"identifiers":["doc:\/\/Afluent\/documentation\/Afluent\/AsyncSequences\/RetryAfterFlatMapping\/allSatisfy(_:)","doc:\/\/Afluent\/documentation\/Afluent\/AsyncSequences\/RetryAfterFlatMapping\/assertNoFailure()","doc:\/\/Afluent\/documentation\/Afluent\/AsyncSequences\/RetryAfterFlatMapping\/breakpoint(receiveOutput:receiveError:)","doc:\/\/Afluent\/documentation\/Afluent\/AsyncSequences\/RetryAfterFlatMapping\/breakpointOnError()","doc:\/\/Afluent\/documentation\/Afluent\/AsyncSequences\/RetryAfterFlatMapping\/catch(_:)","doc:\/\/Afluent\/documentation\/Afluent\/AsyncSequences\/RetryAfterFlatMapping\/catch(_:_:)","doc:\/\/Afluent\/documentation\/Afluent\/AsyncSequences\/RetryAfterFlatMapping\/collect()","doc:\/\/Afluent\/documentation\/Afluent\/AsyncSequences\/RetryAfterFlatMapping\/compactMap(_:)-1c4pa","doc:\/\/Afluent\/documentation\/Afluent\/AsyncSequences\/RetryAfterFlatMapping\/compactMap(_:)-89l2h","doc:\/\/Afluent\/documentation\/Afluent\/AsyncSequences\/RetryAfterFlatMapping\/contains(_:)","doc:\/\/Afluent\/documentation\/Afluent\/AsyncSequences\/RetryAfterFlatMapping\/contains(where:)","doc:\/\/Afluent\/documentation\/Afluent\/AsyncSequences\/RetryAfterFlatMapping\/decode(type:decoder:)","doc:\/\/Afluent\/documentation\/Afluent\/AsyncSequences\/RetryAfterFlatMapping\/delay(for:tolerance:)","doc:\/\/Afluent\/documentation\/Afluent\/AsyncSequences\/RetryAfterFlatMapping\/delay(for:tolerance:clock:)","doc:\/\/Afluent\/documentation\/Afluent\/AsyncSequences\/RetryAfterFlatMapping\/dematerialize()","doc:\/\/Afluent\/documentation\/Afluent\/AsyncSequences\/RetryAfterFlatMapping\/discardOutput()","doc:\/\/Afluent\/documentation\/Afluent\/AsyncSequences\/RetryAfterFlatMapping\/drop(while:)","doc:\/\/Afluent\/documentation\/Afluent\/AsyncSequences\/RetryAfterFlatMapping\/dropFirst(_:)","doc:\/\/Afluent\/documentation\/Afluent\/AsyncSequences\/RetryAfterFlatMapping\/encode(encoder:)","doc:\/\/Afluent\/documentation\/Afluent\/AsyncSequences\/RetryAfterFlatMapping\/eraseToAnyAsyncSequence()","doc:\/\/Afluent\/documentation\/Afluent\/AsyncSequences\/RetryAfterFlatMapping\/filter(_:)","doc:\/\/Afluent\/documentation\/Afluent\/AsyncSequences\/RetryAfterFlatMapping\/first()","doc:\/\/Afluent\/documentation\/Afluent\/AsyncSequences\/RetryAfterFlatMapping\/first(where:)","doc:\/\/Afluent\/documentation\/Afluent\/AsyncSequences\/RetryAfterFlatMapping\/flatMap(_:)-4m7nf","doc:\/\/Afluent\/documentation\/Afluent\/AsyncSequences\/RetryAfterFlatMapping\/flatMap(_:)-6w456","doc:\/\/Afluent\/documentation\/Afluent\/AsyncSequences\/RetryAfterFlatMapping\/flatMap(maxSubscriptions:_:)","doc:\/\/Afluent\/documentation\/Afluent\/AsyncSequences\/RetryAfterFlatMapping\/groupBy(keySelector:)","doc:\/\/Afluent\/documentation\/Afluent\/AsyncSequences\/RetryAfterFlatMapping\/handleEvents(receiveMakeIterator:receiveNext:receiveOutput:receiveError:receiveComplete:receiveCancel:)","doc:\/\/Afluent\/documentation\/Afluent\/AsyncSequences\/RetryAfterFlatMapping\/map(_:)-23lae","doc:\/\/Afluent\/documentation\/Afluent\/AsyncSequences\/RetryAfterFlatMapping\/map(_:)-9uds6","doc:\/\/Afluent\/documentation\/Afluent\/AsyncSequences\/RetryAfterFlatMapping\/mapError(_:)","doc:\/\/Afluent\/documentation\/Afluent\/AsyncSequences\/RetryAfterFlatMapping\/mapError(_:_:)","doc:\/\/Afluent\/documentation\/Afluent\/AsyncSequences\/RetryAfterFlatMapping\/materialize()","doc:\/\/Afluent\/documentation\/Afluent\/AsyncSequences\/RetryAfterFlatMapping\/max()","doc:\/\/Afluent\/documentation\/Afluent\/AsyncSequences\/RetryAfterFlatMapping\/max(by:)","doc:\/\/Afluent\/documentation\/Afluent\/AsyncSequences\/RetryAfterFlatMapping\/min()","doc:\/\/Afluent\/documentation\/Afluent\/AsyncSequences\/RetryAfterFlatMapping\/min(by:)","doc:\/\/Afluent\/documentation\/Afluent\/AsyncSequences\/RetryAfterFlatMapping\/prefix(_:)","doc:\/\/Afluent\/documentation\/Afluent\/AsyncSequences\/RetryAfterFlatMapping\/prefix(while:)","doc:\/\/Afluent\/documentation\/Afluent\/AsyncSequences\/RetryAfterFlatMapping\/print(_:)","doc:\/\/Afluent\/documentation\/Afluent\/AsyncSequences\/RetryAfterFlatMapping\/reduce(_:_:)","doc:\/\/Afluent\/documentation\/Afluent\/AsyncSequences\/RetryAfterFlatMapping\/reduce(into:_:)","doc:\/\/Afluent\/documentation\/Afluent\/AsyncSequences\/RetryAfterFlatMapping\/replaceError(with:)","doc:\/\/Afluent\/documentation\/Afluent\/AsyncSequences\/RetryAfterFlatMapping\/replaceNil(with:)","doc:\/\/Afluent\/documentation\/Afluent\/AsyncSequences\/RetryAfterFlatMapping\/retry(_:)","doc:\/\/Afluent\/documentation\/Afluent\/AsyncSequences\/RetryAfterFlatMapping\/retry(_:_:)","doc:\/\/Afluent\/documentation\/Afluent\/AsyncSequences\/RetryAfterFlatMapping\/retry(_:on:)","doc:\/\/Afluent\/documentation\/Afluent\/AsyncSequences\/RetryAfterFlatMapping\/retry(_:on:_:)","doc:\/\/Afluent\/documentation\/Afluent\/AsyncSequences\/RetryAfterFlatMapping\/sink(receiveCompletion:receiveOutput:)","doc:\/\/Afluent\/documentation\/Afluent\/AsyncSequences\/RetryAfterFlatMapping\/throttle(for:clock:latest:)","doc:\/\/Afluent\/documentation\/Afluent\/AsyncSequences\/RetryAfterFlatMapping\/tryCatch(_:)","doc:\/\/Afluent\/documentation\/Afluent\/AsyncSequences\/RetryAfterFlatMapping\/tryCatch(_:_:)"],"title":"Instance Methods","generated":true}],"schemaVersion":{"major":0,"minor":3,"patch":0},"sections":[],"kind":"article","identifier":{"url":"doc:\/\/Afluent\/documentation\/Afluent\/AsyncSequences\/RetryAfterFlatMapping\/AsyncSequence-Implementations","interfaceLanguage":"swift"},"variants":[{"traits":[{"interfaceLanguage":"swift"}],"paths":["\/documentation\/afluent\/asyncsequences\/retryafterflatmapping\/asyncsequence-implementations"]}],"metadata":{"role":"collectionGroup","title":"AsyncSequence Implementations","modules":[{"name":"Afluent"}]},"references":{"doc://Afluent/documentation/Afluent/AsyncSequences/RetryAfterFlatMapping/map(_:)-23lae":{"url":"\/documentation\/afluent\/asyncsequences\/retryafterflatmapping\/map(_:)-23lae","kind":"symbol","title":"map(_:)","identifier":"doc:\/\/Afluent\/documentation\/Afluent\/AsyncSequences\/RetryAfterFlatMapping\/map(_:)-23lae","fragments":[{"text":"func","kind":"keyword"},{"text":" ","kind":"text"},{"kind":"identifier","text":"map"},{"kind":"text","text":"<"},{"kind":"genericParameter","text":"Transformed"},{"kind":"text","text":">(("},{"text":"Self","kind":"typeIdentifier"},{"kind":"text","text":"."},{"kind":"typeIdentifier","text":"Element"},{"kind":"text","text":") "},{"kind":"keyword","text":"async"},{"text":" ","kind":"text"},{"text":"throws","kind":"keyword"},{"kind":"text","text":" -> "},{"text":"Transformed","kind":"typeIdentifier"},{"text":") -> ","kind":"text"},{"kind":"typeIdentifier","preciseIdentifier":"s:12_Concurrency24AsyncThrowingMapSequenceV","text":"AsyncThrowingMapSequence"},{"text":"<","kind":"text"},{"text":"Self","kind":"typeIdentifier"},{"kind":"text","text":", "},{"text":"Transformed","kind":"typeIdentifier"},{"kind":"text","text":">"}],"abstract":[],"role":"symbol","type":"topic"},"doc://Afluent/documentation/Afluent/AsyncSequences/RetryAfterFlatMapping/replaceError(with:)":{"conformance":{"availabilityPrefix":[{"type":"text","text":"Available when"}],"conformancePrefix":[{"type":"text","text":"Conforms when"}],"constraints":[{"code":"Self","type":"codeVoice"},{"text":" conforms to ","type":"text"},{"code":"Sendable","type":"codeVoice"},{"text":".","type":"text"}]},"identifier":"doc:\/\/Afluent\/documentation\/Afluent\/AsyncSequences\/RetryAfterFlatMapping\/replaceError(with:)","abstract":[{"type":"text","text":"Replaces any errors from the upstream "},{"type":"codeVoice","code":"AsyncSequence"},{"type":"text","text":" with the provided value."}],"role":"symbol","url":"\/documentation\/afluent\/asyncsequences\/retryafterflatmapping\/replaceerror(with:)","type":"topic","fragments":[{"text":"func","kind":"keyword"},{"kind":"text","text":" "},{"kind":"identifier","text":"replaceError"},{"kind":"text","text":"("},{"kind":"externalParam","text":"with"},{"text":": ","kind":"text"},{"kind":"typeIdentifier","text":"Self"},{"kind":"text","text":"."},{"text":"Element","kind":"typeIdentifier"},{"text":") -> ","kind":"text"},{"kind":"typeIdentifier","text":"AsyncSequences","preciseIdentifier":"s:7Afluent14AsyncSequencesO"},{"text":".","kind":"text"},{"preciseIdentifier":"s:7Afluent14AsyncSequencesO12ReplaceErrorV","text":"ReplaceError","kind":"typeIdentifier"},{"kind":"text","text":"<"},{"text":"Self","kind":"typeIdentifier"},{"text":", ","kind":"text"},{"kind":"typeIdentifier","text":"Self"},{"text":".","kind":"text"},{"text":"Element","kind":"typeIdentifier"},{"kind":"text","text":">"}],"kind":"symbol","title":"replaceError(with:)"},"doc://Afluent/documentation/Afluent/AsyncSequences/RetryAfterFlatMapping/mapError(_:)":{"title":"mapError(_:)","role":"symbol","fragments":[{"text":"func","kind":"keyword"},{"text":" ","kind":"text"},{"kind":"identifier","text":"mapError"},{"kind":"text","text":"(("},{"kind":"typeIdentifier","text":"Error","preciseIdentifier":"s:s5ErrorP"},{"text":") -> ","kind":"text"},{"kind":"typeIdentifier","preciseIdentifier":"s:s5ErrorP","text":"Error"},{"kind":"text","text":") -> "},{"preciseIdentifier":"s:7Afluent14AsyncSequencesO","text":"AsyncSequences","kind":"typeIdentifier"},{"kind":"text","text":"."},{"kind":"typeIdentifier","preciseIdentifier":"s:7Afluent14AsyncSequencesO8MapErrorV","text":"MapError"},{"text":"<","kind":"text"},{"text":"Self","kind":"typeIdentifier"},{"text":">","kind":"text"}],"url":"\/documentation\/afluent\/asyncsequences\/retryafterflatmapping\/maperror(_:)","identifier":"doc:\/\/Afluent\/documentation\/Afluent\/AsyncSequences\/RetryAfterFlatMapping\/mapError(_:)","kind":"symbol","type":"topic","conformance":{"availabilityPrefix":[{"type":"text","text":"Available when"}],"conformancePrefix":[{"text":"Conforms when","type":"text"}],"constraints":[{"code":"Self","type":"codeVoice"},{"type":"text","text":" conforms to "},{"type":"codeVoice","code":"Sendable"},{"text":".","type":"text"}]},"abstract":[{"type":"text","text":"Transforms the error produced by the "},{"type":"codeVoice","code":"AsyncSequence"},{"type":"text","text":"."}]},"doc://Afluent/documentation/Afluent/AsyncSequences/RetryAfterFlatMapping/eraseToAnyAsyncSequence()":{"role":"symbol","abstract":[{"text":"Type erases the current sequence, useful when you need a concrete type that’s easy to predict.","type":"text"}],"identifier":"doc:\/\/Afluent\/documentation\/Afluent\/AsyncSequences\/RetryAfterFlatMapping\/eraseToAnyAsyncSequence()","url":"\/documentation\/afluent\/asyncsequences\/retryafterflatmapping\/erasetoanyasyncsequence()","type":"topic","fragments":[{"kind":"keyword","text":"func"},{"kind":"text","text":" "},{"kind":"identifier","text":"eraseToAnyAsyncSequence"},{"kind":"text","text":"() -> "},{"text":"AsyncSequences","kind":"typeIdentifier","preciseIdentifier":"s:7Afluent14AsyncSequencesO"},{"text":".","kind":"text"},{"text":"AnyAsyncSequence","preciseIdentifier":"s:7Afluent14AsyncSequencesO03AnyB8SequenceV","kind":"typeIdentifier"},{"text":"<","kind":"text"},{"text":"Self","kind":"typeIdentifier"},{"text":".","kind":"text"},{"text":"Element","kind":"typeIdentifier"},{"kind":"text","text":">"}],"kind":"symbol","conformance":{"availabilityPrefix":[{"text":"Available when","type":"text"}],"conformancePrefix":[{"text":"Conforms when","type":"text"}],"constraints":[{"type":"codeVoice","code":"Self"},{"type":"text","text":" conforms to "},{"type":"codeVoice","code":"Sendable"},{"type":"text","text":" and "},{"type":"codeVoice","code":"Element"},{"type":"text","text":" conforms to "},{"code":"Sendable","type":"codeVoice"},{"type":"text","text":"."}]},"title":"eraseToAnyAsyncSequence()"},"doc://Afluent/documentation/Afluent/AsyncSequences/RetryAfterFlatMapping/flatMap(_:)-6w456":{"identifier":"doc:\/\/Afluent\/documentation\/Afluent\/AsyncSequences\/RetryAfterFlatMapping\/flatMap(_:)-6w456","title":"flatMap(_:)","kind":"symbol","url":"\/documentation\/afluent\/asyncsequences\/retryafterflatmapping\/flatmap(_:)-6w456","type":"topic","role":"symbol","abstract":[],"fragments":[{"kind":"keyword","text":"func"},{"text":" ","kind":"text"},{"kind":"identifier","text":"flatMap"},{"text":"<","kind":"text"},{"kind":"genericParameter","text":"SegmentOfResult"},{"text":">((","kind":"text"},{"text":"Self","kind":"typeIdentifier"},{"text":".","kind":"text"},{"kind":"typeIdentifier","text":"Element"},{"kind":"text","text":") "},{"text":"async","kind":"keyword"},{"text":" ","kind":"text"},{"text":"throws","kind":"keyword"},{"text":" -> ","kind":"text"},{"kind":"typeIdentifier","text":"SegmentOfResult"},{"kind":"text","text":") -> "},{"kind":"typeIdentifier","text":"AsyncThrowingFlatMapSequence","preciseIdentifier":"s:12_Concurrency28AsyncThrowingFlatMapSequenceV"},{"kind":"text","text":"<"},{"text":"Self","kind":"typeIdentifier"},{"text":", ","kind":"text"},{"text":"SegmentOfResult","kind":"typeIdentifier"},{"text":">","kind":"text"}]},"doc://Afluent/documentation/Afluent/AsyncSequences/RetryAfterFlatMapping/min(by:)":{"url":"\/documentation\/afluent\/asyncsequences\/retryafterflatmapping\/min(by:)","identifier":"doc:\/\/Afluent\/documentation\/Afluent\/AsyncSequences\/RetryAfterFlatMapping\/min(by:)","title":"min(by:)","fragments":[{"kind":"keyword","text":"func"},{"text":" ","kind":"text"},{"kind":"identifier","text":"min"},{"kind":"text","text":"("},{"kind":"externalParam","text":"by"},{"text":": (","kind":"text"},{"kind":"typeIdentifier","text":"Self"},{"kind":"text","text":"."},{"text":"Element","kind":"typeIdentifier"},{"kind":"text","text":", "},{"text":"Self","kind":"typeIdentifier"},{"text":".","kind":"text"},{"text":"Element","kind":"typeIdentifier"},{"kind":"text","text":") "},{"kind":"keyword","text":"async"},{"kind":"text","text":" "},{"text":"throws","kind":"keyword"},{"kind":"text","text":" -> "},{"preciseIdentifier":"s:Sb","kind":"typeIdentifier","text":"Bool"},{"text":") ","kind":"text"},{"kind":"keyword","text":"async"},{"kind":"text","text":" "},{"text":"rethrows","kind":"keyword"},{"text":" -> ","kind":"text"},{"kind":"typeIdentifier","text":"Self"},{"kind":"text","text":"."},{"text":"Element","kind":"typeIdentifier"},{"kind":"text","text":"?"}],"type":"topic","kind":"symbol","abstract":[],"role":"symbol"},"doc://Afluent/documentation/Afluent/AsyncSequences/RetryAfterFlatMapping/reduce(into:_:)":{"kind":"symbol","url":"\/documentation\/afluent\/asyncsequences\/retryafterflatmapping\/reduce(into:_:)","role":"symbol","identifier":"doc:\/\/Afluent\/documentation\/Afluent\/AsyncSequences\/RetryAfterFlatMapping\/reduce(into:_:)","fragments":[{"kind":"keyword","text":"func"},{"text":" ","kind":"text"},{"text":"reduce","kind":"identifier"},{"text":"<","kind":"text"},{"text":"Result","kind":"genericParameter"},{"kind":"text","text":">("},{"text":"into","kind":"externalParam"},{"kind":"text","text":": "},{"kind":"typeIdentifier","text":"Result"},{"text":", (","kind":"text"},{"kind":"keyword","text":"inout"},{"kind":"text","text":" "},{"kind":"typeIdentifier","text":"Result"},{"text":", ","kind":"text"},{"kind":"typeIdentifier","text":"Self"},{"kind":"text","text":"."},{"text":"Element","kind":"typeIdentifier"},{"text":") ","kind":"text"},{"text":"async","kind":"keyword"},{"kind":"text","text":" "},{"kind":"keyword","text":"throws"},{"kind":"text","text":" -> "},{"preciseIdentifier":"s:s4Voida","kind":"typeIdentifier","text":"Void"},{"kind":"text","text":") "},{"text":"async","kind":"keyword"},{"text":" ","kind":"text"},{"kind":"keyword","text":"rethrows"},{"text":" -> ","kind":"text"},{"text":"Result","kind":"typeIdentifier"}],"title":"reduce(into:_:)","type":"topic","abstract":[]},"doc://Afluent/documentation/Afluent/AsyncSequences/RetryAfterFlatMapping/retry(_:on:_:)":{"title":"retry(_:on:_:)","identifier":"doc:\/\/Afluent\/documentation\/Afluent\/AsyncSequences\/RetryAfterFlatMapping\/retry(_:on:_:)","url":"\/documentation\/afluent\/asyncsequences\/retryafterflatmapping\/retry(_:on:_:)","role":"symbol","fragments":[{"kind":"keyword","text":"func"},{"kind":"text","text":" "},{"kind":"identifier","text":"retry"},{"kind":"text","text":"<"},{"kind":"genericParameter","text":"D"},{"kind":"text","text":", "},{"text":"E","kind":"genericParameter"},{"text":">(","kind":"text"},{"text":"UInt","kind":"typeIdentifier","preciseIdentifier":"s:Su"},{"text":", ","kind":"text"},{"kind":"externalParam","text":"on"},{"text":": ","kind":"text"},{"text":"E","kind":"typeIdentifier"},{"text":", (","kind":"text"},{"text":"E","kind":"typeIdentifier"},{"kind":"text","text":") "},{"text":"async","kind":"keyword"},{"text":" ","kind":"text"},{"text":"throws","kind":"keyword"},{"kind":"text","text":" -> "},{"text":"D","kind":"typeIdentifier"},{"text":") -> ","kind":"text"},{"kind":"typeIdentifier","preciseIdentifier":"s:7Afluent14AsyncSequencesO","text":"AsyncSequences"},{"kind":"text","text":"."},{"kind":"typeIdentifier","preciseIdentifier":"s:7Afluent14AsyncSequencesO23RetryOnAfterFlatMappingC","text":"RetryOnAfterFlatMapping"},{"kind":"text","text":"<"},{"kind":"typeIdentifier","text":"Self"},{"text":", ","kind":"text"},{"kind":"typeIdentifier","text":"E"},{"kind":"text","text":", "},{"text":"D","kind":"typeIdentifier"},{"text":">","kind":"text"}],"kind":"symbol","conformance":{"availabilityPrefix":[{"text":"Available when","type":"text"}],"conformancePrefix":[{"type":"text","text":"Conforms when"}],"constraints":[{"type":"codeVoice","code":"Self"},{"text":" conforms to ","type":"text"},{"type":"codeVoice","code":"Sendable"},{"type":"text","text":"."}]},"abstract":[{"type":"text","text":"Retries the upstream "},{"code":"AsynchronousUnitOfWork","type":"codeVoice"},{"text":" up to a specified number of times only when a specific error occurs, while applying a transformation on error.","type":"text"}],"type":"topic"},"doc://Afluent/documentation/Afluent/AsyncSequences/RetryAfterFlatMapping/collect()":{"type":"topic","kind":"symbol","title":"collect()","url":"\/documentation\/afluent\/asyncsequences\/retryafterflatmapping\/collect()","fragments":[{"text":"func","kind":"keyword"},{"kind":"text","text":" "},{"text":"collect","kind":"identifier"},{"kind":"text","text":"() -> "},{"kind":"typeIdentifier","preciseIdentifier":"s:7Afluent14AsyncSequencesO","text":"AsyncSequences"},{"kind":"text","text":"."},{"text":"Collect","preciseIdentifier":"s:7Afluent14AsyncSequencesO7CollectV","kind":"typeIdentifier"},{"kind":"text","text":"<"},{"kind":"typeIdentifier","text":"Self"},{"kind":"text","text":">"}],"conformance":{"conformancePrefix":[{"type":"text","text":"Conforms when"}],"availabilityPrefix":[{"type":"text","text":"Available when"}],"constraints":[{"code":"Self","type":"codeVoice"},{"type":"text","text":" conforms to "},{"code":"Sendable","type":"codeVoice"},{"type":"text","text":"."}]},"identifier":"doc:\/\/Afluent\/documentation\/Afluent\/AsyncSequences\/RetryAfterFlatMapping\/collect()","abstract":[{"type":"text","text":"Collects all received elements, and emits a single array of the collection when the upstream sequence finishes."}],"role":"symbol"},"doc://Afluent/documentation/Afluent/AsyncSequences/RetryAfterFlatMapping/min()":{"conformance":{"availabilityPrefix":[{"type":"text","text":"Available when"}],"conformancePrefix":[{"text":"Conforms when","type":"text"}],"constraints":[{"code":"Element","type":"codeVoice"},{"text":" conforms to ","type":"text"},{"code":"Comparable","type":"codeVoice"},{"text":".","type":"text"}]},"identifier":"doc:\/\/Afluent\/documentation\/Afluent\/AsyncSequences\/RetryAfterFlatMapping\/min()","abstract":[],"role":"symbol","url":"\/documentation\/afluent\/asyncsequences\/retryafterflatmapping\/min()","type":"topic","fragments":[{"kind":"keyword","text":"func"},{"text":" ","kind":"text"},{"text":"min","kind":"identifier"},{"text":"() ","kind":"text"},{"text":"async","kind":"keyword"},{"kind":"text","text":" "},{"kind":"keyword","text":"rethrows"},{"kind":"text","text":" -> "},{"text":"Self","kind":"typeIdentifier"},{"kind":"text","text":"."},{"text":"Element","kind":"typeIdentifier"},{"kind":"text","text":"?"}],"title":"min()","kind":"symbol"},"doc://Afluent/documentation/Afluent/AsyncSequences/RetryAfterFlatMapping/max(by:)":{"kind":"symbol","url":"\/documentation\/afluent\/asyncsequences\/retryafterflatmapping\/max(by:)","role":"symbol","identifier":"doc:\/\/Afluent\/documentation\/Afluent\/AsyncSequences\/RetryAfterFlatMapping\/max(by:)","fragments":[{"text":"func","kind":"keyword"},{"kind":"text","text":" "},{"text":"max","kind":"identifier"},{"kind":"text","text":"("},{"kind":"externalParam","text":"by"},{"kind":"text","text":": ("},{"kind":"typeIdentifier","text":"Self"},{"text":".","kind":"text"},{"text":"Element","kind":"typeIdentifier"},{"kind":"text","text":", "},{"kind":"typeIdentifier","text":"Self"},{"kind":"text","text":"."},{"kind":"typeIdentifier","text":"Element"},{"kind":"text","text":") "},{"kind":"keyword","text":"async"},{"text":" ","kind":"text"},{"text":"throws","kind":"keyword"},{"text":" -> ","kind":"text"},{"kind":"typeIdentifier","text":"Bool","preciseIdentifier":"s:Sb"},{"text":") ","kind":"text"},{"text":"async","kind":"keyword"},{"kind":"text","text":" "},{"kind":"keyword","text":"rethrows"},{"kind":"text","text":" -> "},{"kind":"typeIdentifier","text":"Self"},{"text":".","kind":"text"},{"text":"Element","kind":"typeIdentifier"},{"text":"?","kind":"text"}],"title":"max(by:)","type":"topic","abstract":[]},"doc://Afluent/documentation/Afluent/AsyncSequences/RetryAfterFlatMapping/materialize()":{"abstract":[{"type":"text","text":"Transforms the elements, completion, and errors of the current "},{"code":"AsyncSequence","type":"codeVoice"},{"type":"text","text":" into "},{"type":"codeVoice","code":"Event"},{"type":"text","text":" values."}],"identifier":"doc:\/\/Afluent\/documentation\/Afluent\/AsyncSequences\/RetryAfterFlatMapping\/materialize()","conformance":{"conformancePrefix":[{"text":"Conforms when","type":"text"}],"availabilityPrefix":[{"text":"Available when","type":"text"}],"constraints":[{"code":"Self","type":"codeVoice"},{"type":"text","text":" conforms to "},{"type":"codeVoice","code":"Sendable"},{"text":".","type":"text"}]},"fragments":[{"text":"func","kind":"keyword"},{"text":" ","kind":"text"},{"text":"materialize","kind":"identifier"},{"text":"() -> ","kind":"text"},{"kind":"typeIdentifier","preciseIdentifier":"s:7Afluent14AsyncSequencesO","text":"AsyncSequences"},{"text":".","kind":"text"},{"kind":"typeIdentifier","text":"Materialize","preciseIdentifier":"s:7Afluent14AsyncSequencesO11MaterializeV"},{"text":"<","kind":"text"},{"text":"Self","kind":"typeIdentifier"},{"kind":"text","text":">"}],"kind":"symbol","url":"\/documentation\/afluent\/asyncsequences\/retryafterflatmapping\/materialize()","title":"materialize()","role":"symbol","type":"topic"},"doc://Afluent/documentation/Afluent/AsyncSequences/RetryAfterFlatMapping/replaceNil(with:)":{"kind":"symbol","url":"\/documentation\/afluent\/asyncsequences\/retryafterflatmapping\/replacenil(with:)","identifier":"doc:\/\/Afluent\/documentation\/Afluent\/AsyncSequences\/RetryAfterFlatMapping\/replaceNil(with:)","type":"topic","fragments":[{"text":"func","kind":"keyword"},{"text":" ","kind":"text"},{"text":"replaceNil","kind":"identifier"},{"text":"<","kind":"text"},{"text":"E","kind":"genericParameter"},{"kind":"text","text":">("},{"text":"with","kind":"externalParam"},{"kind":"text","text":": "},{"text":"E","kind":"typeIdentifier"},{"text":") -> ","kind":"text"},{"text":"AsyncSequences","kind":"typeIdentifier","preciseIdentifier":"s:7Afluent14AsyncSequencesO"},{"kind":"text","text":"."},{"text":"ReplaceNil","kind":"typeIdentifier","preciseIdentifier":"s:7Afluent14AsyncSequencesO10ReplaceNilV"},{"text":"<","kind":"text"},{"kind":"typeIdentifier","text":"Self"},{"kind":"text","text":", "},{"kind":"typeIdentifier","text":"E"},{"kind":"text","text":">"}],"title":"replaceNil(with:)","conformance":{"availabilityPrefix":[{"text":"Available when","type":"text"}],"conformancePrefix":[{"type":"text","text":"Conforms when"}],"constraints":[{"code":"Self","type":"codeVoice"},{"text":" conforms to ","type":"text"},{"code":"Sendable","type":"codeVoice"},{"text":".","type":"text"}]},"abstract":[{"text":"Replaces any ","type":"text"},{"code":"nil","type":"codeVoice"},{"type":"text","text":" values from the upstream "},{"type":"codeVoice","code":"AsyncSequence"},{"text":" with the provided non-nil value.","type":"text"}],"role":"symbol"},"doc://Afluent/documentation/Afluent/AsyncSequences/RetryAfterFlatMapping/retry(_:)":{"fragments":[{"text":"func","kind":"keyword"},{"text":" ","kind":"text"},{"text":"retry","kind":"identifier"},{"kind":"text","text":"("},{"kind":"typeIdentifier","text":"UInt","preciseIdentifier":"s:Su"},{"text":") -> ","kind":"text"},{"kind":"typeIdentifier","text":"AsyncSequences","preciseIdentifier":"s:7Afluent14AsyncSequencesO"},{"kind":"text","text":"."},{"text":"Retry","preciseIdentifier":"s:7Afluent14AsyncSequencesO5RetryC","kind":"typeIdentifier"},{"text":"<","kind":"text"},{"kind":"typeIdentifier","text":"Self"},{"kind":"text","text":">"}],"url":"\/documentation\/afluent\/asyncsequences\/retryafterflatmapping\/retry(_:)","kind":"symbol","identifier":"doc:\/\/Afluent\/documentation\/Afluent\/AsyncSequences\/RetryAfterFlatMapping\/retry(_:)","type":"topic","role":"symbol","title":"retry(_:)","abstract":[{"text":"Retries the upstream ","type":"text"},{"type":"codeVoice","code":"AsyncSequence"},{"type":"text","text":" up to a specified number of times."}],"conformance":{"availabilityPrefix":[{"type":"text","text":"Available when"}],"constraints":[{"type":"codeVoice","code":"Self"},{"text":" conforms to ","type":"text"},{"code":"Sendable","type":"codeVoice"},{"type":"text","text":" and "},{"type":"codeVoice","code":"Element"},{"type":"text","text":" conforms to "},{"code":"Sendable","type":"codeVoice"},{"type":"text","text":"."}],"conformancePrefix":[{"type":"text","text":"Conforms when"}]}},"doc://Afluent/documentation/Afluent/AsyncSequences/RetryAfterFlatMapping/filter(_:)":{"url":"\/documentation\/afluent\/asyncsequences\/retryafterflatmapping\/filter(_:)","kind":"symbol","title":"filter(_:)","identifier":"doc:\/\/Afluent\/documentation\/Afluent\/AsyncSequences\/RetryAfterFlatMapping\/filter(_:)","fragments":[{"kind":"keyword","text":"func"},{"text":" ","kind":"text"},{"kind":"identifier","text":"filter"},{"text":"((","kind":"text"},{"kind":"typeIdentifier","text":"Self"},{"kind":"text","text":"."},{"kind":"typeIdentifier","text":"Element"},{"text":") ","kind":"text"},{"text":"async","kind":"keyword"},{"text":" -> ","kind":"text"},{"text":"Bool","kind":"typeIdentifier","preciseIdentifier":"s:Sb"},{"text":") -> ","kind":"text"},{"text":"AsyncFilterSequence","kind":"typeIdentifier","preciseIdentifier":"s:12_Concurrency19AsyncFilterSequenceV"},{"kind":"text","text":"<"},{"text":"Self","kind":"typeIdentifier"},{"kind":"text","text":">"}],"abstract":[],"role":"symbol","type":"topic"},"doc://Afluent/documentation/Afluent/AsyncSequences/RetryAfterFlatMapping/tryCatch(_:_:)":{"role":"symbol","title":"tryCatch(_:_:)","url":"\/documentation\/afluent\/asyncsequences\/retryafterflatmapping\/trycatch(_:_:)","conformance":{"conformancePrefix":[{"type":"text","text":"Conforms when"}],"constraints":[{"code":"Self","type":"codeVoice"},{"type":"text","text":" conforms to "},{"type":"codeVoice","code":"Sendable"},{"text":".","type":"text"}],"availabilityPrefix":[{"text":"Available when","type":"text"}]},"identifier":"doc:\/\/Afluent\/documentation\/Afluent\/AsyncSequences\/RetryAfterFlatMapping\/tryCatch(_:_:)","fragments":[{"kind":"keyword","text":"func"},{"kind":"text","text":" "},{"kind":"identifier","text":"tryCatch"},{"text":"<","kind":"text"},{"text":"D","kind":"genericParameter"},{"text":", ","kind":"text"},{"text":"E","kind":"genericParameter"},{"kind":"text","text":">("},{"kind":"typeIdentifier","text":"E"},{"kind":"text","text":", ("},{"text":"E","kind":"typeIdentifier"},{"kind":"text","text":") "},{"text":"async","kind":"keyword"},{"text":" ","kind":"text"},{"kind":"keyword","text":"throws"},{"text":" -> ","kind":"text"},{"text":"D","kind":"typeIdentifier"},{"text":") -> ","kind":"text"},{"text":"AsyncSequences","kind":"typeIdentifier","preciseIdentifier":"s:7Afluent14AsyncSequencesO"},{"text":".","kind":"text"},{"kind":"typeIdentifier","text":"Catch","preciseIdentifier":"s:7Afluent14AsyncSequencesO5CatchV"},{"kind":"text","text":"<"},{"text":"Self","kind":"typeIdentifier"},{"kind":"text","text":", "},{"text":"D","kind":"typeIdentifier"},{"text":">","kind":"text"}],"abstract":[{"type":"text","text":"Tries to catch a specific type of error emitted by the upstream "},{"code":"AsyncSequence","type":"codeVoice"},{"type":"text","text":" and handles them using the provided throwing closure."}],"kind":"symbol","type":"topic"},"doc://Afluent/documentation/Afluent/AsyncSequences/RetryAfterFlatMapping/drop(while:)":{"type":"topic","fragments":[{"kind":"keyword","text":"func"},{"kind":"text","text":" "},{"kind":"identifier","text":"drop"},{"kind":"text","text":"("},{"kind":"externalParam","text":"while"},{"kind":"text","text":": ("},{"kind":"typeIdentifier","text":"Self"},{"text":".","kind":"text"},{"text":"Element","kind":"typeIdentifier"},{"kind":"text","text":") "},{"text":"async","kind":"keyword"},{"kind":"text","text":" -> "},{"preciseIdentifier":"s:Sb","kind":"typeIdentifier","text":"Bool"},{"text":") -> ","kind":"text"},{"text":"AsyncDropWhileSequence","kind":"typeIdentifier","preciseIdentifier":"s:12_Concurrency22AsyncDropWhileSequenceV"},{"text":"<","kind":"text"},{"kind":"typeIdentifier","text":"Self"},{"kind":"text","text":">"}],"url":"\/documentation\/afluent\/asyncsequences\/retryafterflatmapping\/drop(while:)","identifier":"doc:\/\/Afluent\/documentation\/Afluent\/AsyncSequences\/RetryAfterFlatMapping\/drop(while:)","title":"drop(while:)","role":"symbol","kind":"symbol","abstract":[]},"doc://Afluent/documentation/Afluent/AsyncSequences/RetryAfterFlatMapping/catch(_:_:)":{"conformance":{"conformancePrefix":[{"type":"text","text":"Conforms when"}],"availabilityPrefix":[{"type":"text","text":"Available when"}],"constraints":[{"code":"Self","type":"codeVoice"},{"text":" conforms to ","type":"text"},{"type":"codeVoice","code":"Sendable"},{"type":"text","text":"."}]},"fragments":[{"text":"func","kind":"keyword"},{"kind":"text","text":" "},{"kind":"identifier","text":"`catch`"},{"text":"<","kind":"text"},{"kind":"genericParameter","text":"D"},{"kind":"text","text":", "},{"text":"E","kind":"genericParameter"},{"text":">(","kind":"text"},{"text":"E","kind":"typeIdentifier"},{"kind":"text","text":", ("},{"text":"E","kind":"typeIdentifier"},{"kind":"text","text":") "},{"kind":"keyword","text":"async"},{"text":" -> ","kind":"text"},{"kind":"typeIdentifier","text":"D"},{"text":") -> ","kind":"text"},{"kind":"typeIdentifier","preciseIdentifier":"s:7Afluent14AsyncSequencesO","text":"AsyncSequences"},{"kind":"text","text":"."},{"text":"Catch","preciseIdentifier":"s:7Afluent14AsyncSequencesO5CatchV","kind":"typeIdentifier"},{"kind":"text","text":"<"},{"text":"Self","kind":"typeIdentifier"},{"text":", ","kind":"text"},{"text":"D","kind":"typeIdentifier"},{"text":">","kind":"text"}],"identifier":"doc:\/\/Afluent\/documentation\/Afluent\/AsyncSequences\/RetryAfterFlatMapping\/catch(_:_:)","url":"\/documentation\/afluent\/asyncsequences\/retryafterflatmapping\/catch(_:_:)","role":"symbol","abstract":[{"type":"text","text":"Catches a specific type of error emitted by the upstream "},{"type":"codeVoice","code":"AsyncSequence"},{"text":" and handles them using the provided closure.","type":"text"}],"title":"catch(_:_:)","type":"topic","kind":"symbol"},"doc://Afluent/documentation/Afluent/AsyncSequences/RetryAfterFlatMapping/tryCatch(_:)":{"abstract":[{"type":"text","text":"Tries to catch any errors emitted by the upstream "},{"type":"codeVoice","code":"AsyncSequence"},{"type":"text","text":" and handles them using the provided throwing closure."}],"type":"topic","fragments":[{"kind":"keyword","text":"func"},{"kind":"text","text":" "},{"kind":"identifier","text":"tryCatch"},{"text":"<","kind":"text"},{"kind":"genericParameter","text":"D"},{"kind":"text","text":">(("},{"preciseIdentifier":"s:s5ErrorP","text":"Error","kind":"typeIdentifier"},{"kind":"text","text":") "},{"text":"async","kind":"keyword"},{"kind":"text","text":" "},{"text":"throws","kind":"keyword"},{"text":" -> ","kind":"text"},{"text":"D","kind":"typeIdentifier"},{"kind":"text","text":") -> "},{"text":"AsyncSequences","kind":"typeIdentifier","preciseIdentifier":"s:7Afluent14AsyncSequencesO"},{"text":".","kind":"text"},{"text":"Catch","preciseIdentifier":"s:7Afluent14AsyncSequencesO5CatchV","kind":"typeIdentifier"},{"kind":"text","text":"<"},{"kind":"typeIdentifier","text":"Self"},{"kind":"text","text":", "},{"text":"D","kind":"typeIdentifier"},{"text":">","kind":"text"}],"url":"\/documentation\/afluent\/asyncsequences\/retryafterflatmapping\/trycatch(_:)","conformance":{"constraints":[{"type":"codeVoice","code":"Self"},{"type":"text","text":" conforms to "},{"type":"codeVoice","code":"Sendable"},{"text":".","type":"text"}],"conformancePrefix":[{"text":"Conforms when","type":"text"}],"availabilityPrefix":[{"text":"Available when","type":"text"}]},"identifier":"doc:\/\/Afluent\/documentation\/Afluent\/AsyncSequences\/RetryAfterFlatMapping\/tryCatch(_:)","kind":"symbol","title":"tryCatch(_:)","role":"symbol"},"doc://Afluent/documentation/Afluent/AsyncSequences/RetryAfterFlatMapping/assertNoFailure()":{"conformance":{"availabilityPrefix":[{"text":"Available when","type":"text"}],"constraints":[{"type":"codeVoice","code":"Self"},{"text":" conforms to ","type":"text"},{"type":"codeVoice","code":"Sendable"},{"text":".","type":"text"}],"conformancePrefix":[{"type":"text","text":"Conforms when"}]},"type":"topic","identifier":"doc:\/\/Afluent\/documentation\/Afluent\/AsyncSequences\/RetryAfterFlatMapping\/assertNoFailure()","fragments":[{"kind":"keyword","text":"func"},{"kind":"text","text":" "},{"kind":"identifier","text":"assertNoFailure"},{"kind":"text","text":"() -> "},{"preciseIdentifier":"s:7Afluent14AsyncSequencesO","text":"AsyncSequences","kind":"typeIdentifier"},{"text":".","kind":"text"},{"kind":"typeIdentifier","preciseIdentifier":"s:7Afluent14AsyncSequencesO15AssertNoFailureV","text":"AssertNoFailure"},{"kind":"text","text":"<"},{"kind":"typeIdentifier","text":"Self"},{"text":">","kind":"text"}],"role":"symbol","kind":"symbol","url":"\/documentation\/afluent\/asyncsequences\/retryafterflatmapping\/assertnofailure()","abstract":[{"type":"text","text":"Raises a fatal error when its upstream sequence fails, and otherwise republishes all received input."}],"title":"assertNoFailure()"},"doc://Afluent/documentation/Afluent/AsyncSequences/RetryAfterFlatMapping/contains(_:)":{"abstract":[],"conformance":{"constraints":[{"type":"codeVoice","code":"Element"},{"type":"text","text":" conforms to "},{"type":"codeVoice","code":"Equatable"},{"text":".","type":"text"}],"availabilityPrefix":[{"type":"text","text":"Available when"}],"conformancePrefix":[{"type":"text","text":"Conforms when"}]},"role":"symbol","kind":"symbol","url":"\/documentation\/afluent\/asyncsequences\/retryafterflatmapping\/contains(_:)","type":"topic","fragments":[{"text":"func","kind":"keyword"},{"text":" ","kind":"text"},{"kind":"identifier","text":"contains"},{"text":"(","kind":"text"},{"kind":"typeIdentifier","text":"Self"},{"kind":"text","text":"."},{"kind":"typeIdentifier","text":"Element"},{"kind":"text","text":") "},{"kind":"keyword","text":"async"},{"text":" ","kind":"text"},{"text":"rethrows","kind":"keyword"},{"kind":"text","text":" -> "},{"preciseIdentifier":"s:Sb","text":"Bool","kind":"typeIdentifier"}],"title":"contains(_:)","identifier":"doc:\/\/Afluent\/documentation\/Afluent\/AsyncSequences\/RetryAfterFlatMapping\/contains(_:)"},"doc://Afluent/documentation/Afluent/AsyncSequences/RetryAfterFlatMapping/mapError(_:_:)":{"url":"\/documentation\/afluent\/asyncsequences\/retryafterflatmapping\/maperror(_:_:)","kind":"symbol","conformance":{"availabilityPrefix":[{"text":"Available when","type":"text"}],"conformancePrefix":[{"type":"text","text":"Conforms when"}],"constraints":[{"code":"Self","type":"codeVoice"},{"text":" conforms to ","type":"text"},{"code":"Sendable","type":"codeVoice"},{"type":"text","text":"."}]},"title":"mapError(_:_:)","identifier":"doc:\/\/Afluent\/documentation\/Afluent\/AsyncSequences\/RetryAfterFlatMapping\/mapError(_:_:)","fragments":[{"text":"func","kind":"keyword"},{"text":" ","kind":"text"},{"kind":"identifier","text":"mapError"},{"kind":"text","text":"<"},{"kind":"genericParameter","text":"E"},{"text":">(","kind":"text"},{"kind":"typeIdentifier","text":"E"},{"text":", (","kind":"text"},{"preciseIdentifier":"s:s5ErrorP","text":"Error","kind":"typeIdentifier"},{"kind":"text","text":") -> "},{"preciseIdentifier":"s:s5ErrorP","kind":"typeIdentifier","text":"Error"},{"kind":"text","text":") -> "},{"text":"AsyncSequences","kind":"typeIdentifier","preciseIdentifier":"s:7Afluent14AsyncSequencesO"},{"kind":"text","text":"."},{"preciseIdentifier":"s:7Afluent14AsyncSequencesO8MapErrorV","kind":"typeIdentifier","text":"MapError"},{"text":"<","kind":"text"},{"kind":"typeIdentifier","text":"Self"},{"text":">","kind":"text"}],"abstract":[{"type":"text","text":"Transforms the error produced by the "},{"type":"codeVoice","code":"AsyncSequence"},{"text":".","type":"text"}],"role":"symbol","type":"topic"},"doc://Afluent/documentation/Afluent/AsyncSequences/RetryAfterFlatMapping/unicodeScalars":{"role":"symbol","conformance":{"constraints":[{"type":"codeVoice","code":"Element"},{"text":" is ","type":"text"},{"type":"codeVoice","code":"UInt8"},{"type":"text","text":"."}],"conformancePrefix":[{"type":"text","text":"Conforms when"}],"availabilityPrefix":[{"type":"text","text":"Available when"}]},"identifier":"doc:\/\/Afluent\/documentation\/Afluent\/AsyncSequences\/RetryAfterFlatMapping\/unicodeScalars","title":"unicodeScalars","abstract":[],"type":"topic","url":"\/documentation\/afluent\/asyncsequences\/retryafterflatmapping\/unicodescalars","kind":"symbol","fragments":[{"kind":"keyword","text":"var"},{"kind":"text","text":" "},{"text":"unicodeScalars","kind":"identifier"},{"kind":"text","text":": "},{"text":"AsyncUnicodeScalarSequence","preciseIdentifier":"s:10Foundation26AsyncUnicodeScalarSequenceV","kind":"typeIdentifier"},{"kind":"text","text":"<"},{"text":"Self","kind":"typeIdentifier"},{"text":">","kind":"text"}]},"doc://Afluent/documentation/Afluent/AsyncSequences/RetryAfterFlatMapping/print(_:)":{"identifier":"doc:\/\/Afluent\/documentation\/Afluent\/AsyncSequences\/RetryAfterFlatMapping\/print(_:)","type":"topic","fragments":[{"text":"func","kind":"keyword"},{"kind":"text","text":" "},{"kind":"identifier","text":"print"},{"text":"(","kind":"text"},{"preciseIdentifier":"s:SS","kind":"typeIdentifier","text":"String"},{"text":") -> ","kind":"text"},{"kind":"typeIdentifier","preciseIdentifier":"s:7Afluent14AsyncSequencesO","text":"AsyncSequences"},{"kind":"text","text":"."},{"text":"HandleEvents","kind":"typeIdentifier","preciseIdentifier":"s:7Afluent14AsyncSequencesO12HandleEventsV"},{"text":"<","kind":"text"},{"text":"Self","kind":"typeIdentifier"},{"kind":"text","text":">"}],"conformance":{"conformancePrefix":[{"text":"Conforms when","type":"text"}],"availabilityPrefix":[{"type":"text","text":"Available when"}],"constraints":[{"type":"codeVoice","code":"Self"},{"type":"text","text":" conforms to "},{"code":"Sendable","type":"codeVoice"},{"type":"text","text":"."}]},"url":"\/documentation\/afluent\/asyncsequences\/retryafterflatmapping\/print(_:)","role":"symbol","kind":"symbol","title":"print(_:)","abstract":[{"type":"text","text":"Logs events from the upstream "},{"code":"AsyncSequence","type":"codeVoice"},{"text":" to the console.","type":"text"}]},"doc://Afluent/documentation/Afluent/AsyncSequences/RetryAfterFlatMapping/prefix(while:)":{"title":"prefix(while:)","abstract":[],"role":"symbol","identifier":"doc:\/\/Afluent\/documentation\/Afluent\/AsyncSequences\/RetryAfterFlatMapping\/prefix(while:)","fragments":[{"text":"func","kind":"keyword"},{"kind":"text","text":" "},{"text":"prefix","kind":"identifier"},{"kind":"text","text":"("},{"text":"while","kind":"externalParam"},{"text":": (","kind":"text"},{"text":"Self","kind":"typeIdentifier"},{"text":".","kind":"text"},{"kind":"typeIdentifier","text":"Element"},{"kind":"text","text":") "},{"kind":"keyword","text":"async"},{"text":" -> ","kind":"text"},{"kind":"typeIdentifier","text":"Bool","preciseIdentifier":"s:Sb"},{"text":") ","kind":"text"},{"kind":"keyword","text":"rethrows"},{"text":" -> ","kind":"text"},{"text":"AsyncPrefixWhileSequence","kind":"typeIdentifier","preciseIdentifier":"s:12_Concurrency24AsyncPrefixWhileSequenceV"},{"text":"<","kind":"text"},{"text":"Self","kind":"typeIdentifier"},{"kind":"text","text":">"}],"kind":"symbol","type":"topic","url":"\/documentation\/afluent\/asyncsequences\/retryafterflatmapping\/prefix(while:)"},"doc://Afluent/documentation/Afluent/AsyncSequences/RetryAfterFlatMapping/first(where:)":{"type":"topic","identifier":"doc:\/\/Afluent\/documentation\/Afluent\/AsyncSequences\/RetryAfterFlatMapping\/first(where:)","fragments":[{"text":"func","kind":"keyword"},{"kind":"text","text":" "},{"text":"first","kind":"identifier"},{"text":"(","kind":"text"},{"text":"where","kind":"externalParam"},{"text":": (","kind":"text"},{"kind":"typeIdentifier","text":"Self"},{"kind":"text","text":"."},{"kind":"typeIdentifier","text":"Element"},{"kind":"text","text":") "},{"text":"async","kind":"keyword"},{"kind":"text","text":" "},{"kind":"keyword","text":"throws"},{"kind":"text","text":" -> "},{"preciseIdentifier":"s:Sb","kind":"typeIdentifier","text":"Bool"},{"text":") ","kind":"text"},{"text":"async","kind":"keyword"},{"kind":"text","text":" "},{"kind":"keyword","text":"rethrows"},{"text":" -> ","kind":"text"},{"text":"Self","kind":"typeIdentifier"},{"kind":"text","text":"."},{"text":"Element","kind":"typeIdentifier"},{"kind":"text","text":"?"}],"role":"symbol","kind":"symbol","abstract":[],"title":"first(where:)","url":"\/documentation\/afluent\/asyncsequences\/retryafterflatmapping\/first(where:)"},"doc://Afluent/documentation/Afluent/AsyncSequences/RetryAfterFlatMapping/max()":{"url":"\/documentation\/afluent\/asyncsequences\/retryafterflatmapping\/max()","kind":"symbol","conformance":{"conformancePrefix":[{"type":"text","text":"Conforms when"}],"availabilityPrefix":[{"type":"text","text":"Available when"}],"constraints":[{"type":"codeVoice","code":"Element"},{"type":"text","text":" conforms to "},{"code":"Comparable","type":"codeVoice"},{"text":".","type":"text"}]},"title":"max()","identifier":"doc:\/\/Afluent\/documentation\/Afluent\/AsyncSequences\/RetryAfterFlatMapping\/max()","fragments":[{"text":"func","kind":"keyword"},{"kind":"text","text":" "},{"text":"max","kind":"identifier"},{"kind":"text","text":"() "},{"kind":"keyword","text":"async"},{"text":" ","kind":"text"},{"kind":"keyword","text":"rethrows"},{"kind":"text","text":" -> "},{"text":"Self","kind":"typeIdentifier"},{"kind":"text","text":"."},{"text":"Element","kind":"typeIdentifier"},{"text":"?","kind":"text"}],"abstract":[],"role":"symbol","type":"topic"},"doc://Afluent/documentation/Afluent/AsyncSequences/RetryAfterFlatMapping/compactMap(_:)-89l2h":{"url":"\/documentation\/afluent\/asyncsequences\/retryafterflatmapping\/compactmap(_:)-89l2h","kind":"symbol","title":"compactMap(_:)","identifier":"doc:\/\/Afluent\/documentation\/Afluent\/AsyncSequences\/RetryAfterFlatMapping\/compactMap(_:)-89l2h","fragments":[{"text":"func","kind":"keyword"},{"text":" ","kind":"text"},{"kind":"identifier","text":"compactMap"},{"text":"<","kind":"text"},{"kind":"genericParameter","text":"ElementOfResult"},{"kind":"text","text":">(("},{"text":"Self","kind":"typeIdentifier"},{"kind":"text","text":"."},{"kind":"typeIdentifier","text":"Element"},{"text":") ","kind":"text"},{"kind":"keyword","text":"async"},{"text":" -> ","kind":"text"},{"text":"ElementOfResult","kind":"typeIdentifier"},{"text":"?) -> ","kind":"text"},{"kind":"typeIdentifier","preciseIdentifier":"s:12_Concurrency23AsyncCompactMapSequenceV","text":"AsyncCompactMapSequence"},{"kind":"text","text":"<"},{"text":"Self","kind":"typeIdentifier"},{"kind":"text","text":", "},{"kind":"typeIdentifier","text":"ElementOfResult"},{"text":">","kind":"text"}],"abstract":[],"role":"symbol","type":"topic"},"doc://Afluent/documentation/Afluent/AsyncSequences/RetryAfterFlatMapping/dematerialize()":{"title":"dematerialize()","abstract":[{"text":"Transforms a sequence of ","type":"text"},{"code":"Event","type":"codeVoice"},{"type":"text","text":" values back into their original form in an "},{"type":"codeVoice","code":"AsyncSequence"},{"text":".","type":"text"}],"identifier":"doc:\/\/Afluent\/documentation\/Afluent\/AsyncSequences\/RetryAfterFlatMapping\/dematerialize()","kind":"symbol","role":"symbol","url":"\/documentation\/afluent\/asyncsequences\/retryafterflatmapping\/dematerialize()","type":"topic","conformance":{"conformancePrefix":[{"type":"text","text":"Conforms when"}],"availabilityPrefix":[{"text":"Available when","type":"text"}],"constraints":[{"type":"codeVoice","code":"Self"},{"type":"text","text":" conforms to "},{"code":"Sendable","type":"codeVoice"},{"type":"text","text":"."}]},"fragments":[{"kind":"keyword","text":"func"},{"text":" ","kind":"text"},{"kind":"identifier","text":"dematerialize"},{"kind":"text","text":"<"},{"kind":"genericParameter","text":"T"},{"kind":"text","text":">() -> "},{"text":"AsyncSequences","kind":"typeIdentifier","preciseIdentifier":"s:7Afluent14AsyncSequencesO"},{"text":".","kind":"text"},{"preciseIdentifier":"s:7Afluent14AsyncSequencesO13DematerializeV","text":"Dematerialize","kind":"typeIdentifier"},{"text":"<","kind":"text"},{"text":"Self","kind":"typeIdentifier"},{"kind":"text","text":", "},{"text":"T","kind":"typeIdentifier"},{"kind":"text","text":">"}]},"doc://Afluent/documentation/Afluent/AsyncSequences/RetryAfterFlatMapping/encode(encoder:)":{"identifier":"doc:\/\/Afluent\/documentation\/Afluent\/AsyncSequences\/RetryAfterFlatMapping\/encode(encoder:)","abstract":[{"type":"text","text":"Encodes the output from upstream using a specified encoder."}],"role":"symbol","url":"\/documentation\/afluent\/asyncsequences\/retryafterflatmapping\/encode(encoder:)","type":"topic","kind":"symbol","title":"encode(encoder:)","conformance":{"availabilityPrefix":[{"type":"text","text":"Available when"}],"conformancePrefix":[{"type":"text","text":"Conforms when"}],"constraints":[{"code":"Self","type":"codeVoice"},{"text":" conforms to ","type":"text"},{"type":"codeVoice","code":"Sendable"},{"type":"text","text":"."}]},"fragments":[{"text":"func","kind":"keyword"},{"kind":"text","text":" "},{"text":"encode","kind":"identifier"},{"text":"<","kind":"text"},{"text":"E","kind":"genericParameter"},{"text":">(","kind":"text"},{"text":"encoder","kind":"externalParam"},{"text":": ","kind":"text"},{"kind":"typeIdentifier","text":"E"},{"text":") -> ","kind":"text"},{"text":"AsyncSequences","kind":"typeIdentifier","preciseIdentifier":"s:7Afluent14AsyncSequencesO"},{"kind":"text","text":"."},{"text":"Encode","kind":"typeIdentifier","preciseIdentifier":"s:7Afluent14AsyncSequencesO6EncodeV"},{"kind":"text","text":"<"},{"kind":"typeIdentifier","text":"Self"},{"kind":"text","text":", "},{"kind":"typeIdentifier","text":"E"},{"kind":"text","text":">"}]},"doc://Afluent/documentation/Afluent/AsyncSequences/RetryAfterFlatMapping/delay(for:tolerance:clock:)":{"type":"topic","conformance":{"constraints":[{"type":"codeVoice","code":"Self"},{"text":" conforms to ","type":"text"},{"type":"codeVoice","code":"Sendable"},{"type":"text","text":" and "},{"code":"Element","type":"codeVoice"},{"text":" conforms to ","type":"text"},{"type":"codeVoice","code":"Sendable"},{"text":".","type":"text"}],"conformancePrefix":[{"type":"text","text":"Conforms when"}],"availabilityPrefix":[{"text":"Available when","type":"text"}]},"url":"\/documentation\/afluent\/asyncsequences\/retryafterflatmapping\/delay(for:tolerance:clock:)","role":"symbol","fragments":[{"kind":"keyword","text":"func"},{"kind":"text","text":" "},{"kind":"identifier","text":"delay"},{"text":"<","kind":"text"},{"kind":"genericParameter","text":"C"},{"text":">(","kind":"text"},{"text":"for","kind":"externalParam"},{"text":": ","kind":"text"},{"text":"C","kind":"typeIdentifier"},{"text":".","kind":"text"},{"kind":"typeIdentifier","text":"Duration"},{"kind":"text","text":", "},{"text":"tolerance","kind":"externalParam"},{"text":": ","kind":"text"},{"text":"C","kind":"typeIdentifier"},{"kind":"text","text":"."},{"kind":"typeIdentifier","text":"Duration"},{"text":"?, ","kind":"text"},{"kind":"externalParam","text":"clock"},{"kind":"text","text":": "},{"kind":"typeIdentifier","text":"C"},{"kind":"text","text":") -> "},{"kind":"typeIdentifier","preciseIdentifier":"s:7Afluent14AsyncSequencesO","text":"AsyncSequences"},{"text":".","kind":"text"},{"preciseIdentifier":"s:7Afluent14AsyncSequencesO5DelayV","text":"Delay","kind":"typeIdentifier"},{"kind":"text","text":"<"},{"text":"Self","kind":"typeIdentifier"},{"kind":"text","text":", "},{"kind":"typeIdentifier","text":"C"},{"kind":"text","text":">"}],"identifier":"doc:\/\/Afluent\/documentation\/Afluent\/AsyncSequences\/RetryAfterFlatMapping\/delay(for:tolerance:clock:)","title":"delay(for:tolerance:clock:)","abstract":[{"type":"text","text":"Delays delivery of all output to the downstream receiver by a specified amount of time"}],"kind":"symbol"},"doc://Afluent/documentation/Afluent/AsyncSequences/RetryAfterFlatMapping/decode(type:decoder:)":{"url":"\/documentation\/afluent\/asyncsequences\/retryafterflatmapping\/decode(type:decoder:)","kind":"symbol","conformance":{"conformancePrefix":[{"text":"Conforms when","type":"text"}],"constraints":[{"type":"codeVoice","code":"Self"},{"type":"text","text":" conforms to "},{"code":"Sendable","type":"codeVoice"},{"type":"text","text":"."}],"availabilityPrefix":[{"text":"Available when","type":"text"}]},"title":"decode(type:decoder:)","identifier":"doc:\/\/Afluent\/documentation\/Afluent\/AsyncSequences\/RetryAfterFlatMapping\/decode(type:decoder:)","fragments":[{"kind":"keyword","text":"func"},{"kind":"text","text":" "},{"text":"decode","kind":"identifier"},{"kind":"text","text":"<"},{"kind":"genericParameter","text":"T"},{"text":", ","kind":"text"},{"text":"D","kind":"genericParameter"},{"text":">(","kind":"text"},{"kind":"externalParam","text":"type"},{"text":": ","kind":"text"},{"kind":"typeIdentifier","text":"T"},{"kind":"text","text":".Type, "},{"text":"decoder","kind":"externalParam"},{"kind":"text","text":": "},{"kind":"typeIdentifier","text":"D"},{"text":") -> ","kind":"text"},{"kind":"typeIdentifier","text":"AsyncSequences","preciseIdentifier":"s:7Afluent14AsyncSequencesO"},{"text":".","kind":"text"},{"text":"Decode","preciseIdentifier":"s:7Afluent14AsyncSequencesO6DecodeV","kind":"typeIdentifier"},{"kind":"text","text":"<"},{"text":"Self","kind":"typeIdentifier"},{"text":", ","kind":"text"},{"kind":"typeIdentifier","text":"D"},{"text":", ","kind":"text"},{"text":"T","kind":"typeIdentifier"},{"kind":"text","text":">"}],"abstract":[{"text":"Decodes the output from the upstream using a specified decoder.","type":"text"}],"role":"symbol","type":"topic"},"doc://Afluent/documentation/Afluent/AsyncSequences/RetryAfterFlatMapping/allSatisfy(_:)":{"identifier":"doc:\/\/Afluent\/documentation\/Afluent\/AsyncSequences\/RetryAfterFlatMapping\/allSatisfy(_:)","abstract":[],"type":"topic","kind":"symbol","role":"symbol","url":"\/documentation\/afluent\/asyncsequences\/retryafterflatmapping\/allsatisfy(_:)","title":"allSatisfy(_:)","fragments":[{"kind":"keyword","text":"func"},{"text":" ","kind":"text"},{"text":"allSatisfy","kind":"identifier"},{"kind":"text","text":"(("},{"kind":"typeIdentifier","text":"Self"},{"text":".","kind":"text"},{"text":"Element","kind":"typeIdentifier"},{"kind":"text","text":") "},{"kind":"keyword","text":"async"},{"text":" ","kind":"text"},{"kind":"keyword","text":"throws"},{"text":" -> ","kind":"text"},{"kind":"typeIdentifier","text":"Bool","preciseIdentifier":"s:Sb"},{"kind":"text","text":") "},{"text":"async","kind":"keyword"},{"text":" ","kind":"text"},{"kind":"keyword","text":"rethrows"},{"kind":"text","text":" -> "},{"kind":"typeIdentifier","text":"Bool","preciseIdentifier":"s:Sb"}]},"doc://Afluent/documentation/Afluent/AsyncSequences/RetryAfterFlatMapping/compactMap(_:)-1c4pa":{"identifier":"doc:\/\/Afluent\/documentation\/Afluent\/AsyncSequences\/RetryAfterFlatMapping\/compactMap(_:)-1c4pa","fragments":[{"text":"func","kind":"keyword"},{"text":" ","kind":"text"},{"text":"compactMap","kind":"identifier"},{"text":"<","kind":"text"},{"text":"ElementOfResult","kind":"genericParameter"},{"text":">((","kind":"text"},{"text":"Self","kind":"typeIdentifier"},{"kind":"text","text":"."},{"kind":"typeIdentifier","text":"Element"},{"text":") ","kind":"text"},{"kind":"keyword","text":"async"},{"text":" ","kind":"text"},{"kind":"keyword","text":"throws"},{"text":" -> ","kind":"text"},{"kind":"typeIdentifier","text":"ElementOfResult"},{"text":"?) -> ","kind":"text"},{"preciseIdentifier":"s:12_Concurrency31AsyncThrowingCompactMapSequenceV","text":"AsyncThrowingCompactMapSequence","kind":"typeIdentifier"},{"text":"<","kind":"text"},{"text":"Self","kind":"typeIdentifier"},{"text":", ","kind":"text"},{"kind":"typeIdentifier","text":"ElementOfResult"},{"text":">","kind":"text"}],"type":"topic","role":"symbol","title":"compactMap(_:)","url":"\/documentation\/afluent\/asyncsequences\/retryafterflatmapping\/compactmap(_:)-1c4pa","kind":"symbol","abstract":[]},"doc://Afluent/documentation/Afluent":{"url":"\/documentation\/afluent","identifier":"doc:\/\/Afluent\/documentation\/Afluent","kind":"symbol","abstract":[],"title":"Afluent","type":"topic","role":"collection"},"doc://Afluent/documentation/Afluent/AsyncSequences/RetryAfterFlatMapping/lines":{"conformance":{"conformancePrefix":[{"type":"text","text":"Conforms when"}],"constraints":[{"type":"codeVoice","code":"Element"},{"text":" is ","type":"text"},{"code":"UInt8","type":"codeVoice"},{"type":"text","text":"."}],"availabilityPrefix":[{"text":"Available when","type":"text"}]},"type":"topic","fragments":[{"kind":"keyword","text":"var"},{"text":" ","kind":"text"},{"text":"lines","kind":"identifier"},{"text":": ","kind":"text"},{"kind":"typeIdentifier","text":"AsyncLineSequence","preciseIdentifier":"s:10Foundation17AsyncLineSequenceV"},{"text":"<","kind":"text"},{"text":"Self","kind":"typeIdentifier"},{"kind":"text","text":">"}],"abstract":[],"title":"lines","url":"\/documentation\/afluent\/asyncsequences\/retryafterflatmapping\/lines","identifier":"doc:\/\/Afluent\/documentation\/Afluent\/AsyncSequences\/RetryAfterFlatMapping\/lines","role":"symbol","kind":"symbol"},"doc://Afluent/documentation/Afluent/AsyncSequences/RetryAfterFlatMapping/reduce(_:_:)":{"type":"topic","title":"reduce(_:_:)","kind":"symbol","role":"symbol","fragments":[{"kind":"keyword","text":"func"},{"text":" ","kind":"text"},{"kind":"identifier","text":"reduce"},{"text":"<","kind":"text"},{"text":"Result","kind":"genericParameter"},{"text":">(","kind":"text"},{"text":"Result","kind":"typeIdentifier"},{"text":", (","kind":"text"},{"kind":"typeIdentifier","text":"Result"},{"text":", ","kind":"text"},{"text":"Self","kind":"typeIdentifier"},{"kind":"text","text":"."},{"kind":"typeIdentifier","text":"Element"},{"text":") ","kind":"text"},{"text":"async","kind":"keyword"},{"kind":"text","text":" "},{"kind":"keyword","text":"throws"},{"text":" -> ","kind":"text"},{"kind":"typeIdentifier","text":"Result"},{"text":") ","kind":"text"},{"text":"async","kind":"keyword"},{"text":" ","kind":"text"},{"kind":"keyword","text":"rethrows"},{"text":" -> ","kind":"text"},{"kind":"typeIdentifier","text":"Result"}],"abstract":[],"url":"\/documentation\/afluent\/asyncsequences\/retryafterflatmapping\/reduce(_:_:)","identifier":"doc:\/\/Afluent\/documentation\/Afluent\/AsyncSequences\/RetryAfterFlatMapping\/reduce(_:_:)"},"doc://Afluent/documentation/Afluent/AsyncSequences":{"navigatorTitle":[{"kind":"identifier","text":"AsyncSequences"}],"fragments":[{"kind":"keyword","text":"enum"},{"kind":"text","text":" "},{"kind":"identifier","text":"AsyncSequences"}],"type":"topic","abstract":[{"text":"A namespace for grouping related AsyncSequence operations.","type":"text"}],"kind":"symbol","title":"AsyncSequences","role":"symbol","url":"\/documentation\/afluent\/asyncsequences","identifier":"doc:\/\/Afluent\/documentation\/Afluent\/AsyncSequences"},"doc://Afluent/documentation/Afluent/AsyncSequences/RetryAfterFlatMapping/flatMap(_:)-4m7nf":{"identifier":"doc:\/\/Afluent\/documentation\/Afluent\/AsyncSequences\/RetryAfterFlatMapping\/flatMap(_:)-4m7nf","abstract":[],"role":"symbol","url":"\/documentation\/afluent\/asyncsequences\/retryafterflatmapping\/flatmap(_:)-4m7nf","type":"topic","fragments":[{"kind":"keyword","text":"func"},{"text":" ","kind":"text"},{"text":"flatMap","kind":"identifier"},{"text":"<","kind":"text"},{"kind":"genericParameter","text":"SegmentOfResult"},{"text":">((","kind":"text"},{"text":"Self","kind":"typeIdentifier"},{"kind":"text","text":"."},{"kind":"typeIdentifier","text":"Element"},{"kind":"text","text":") "},{"kind":"keyword","text":"async"},{"text":" -> ","kind":"text"},{"kind":"typeIdentifier","text":"SegmentOfResult"},{"text":") -> ","kind":"text"},{"preciseIdentifier":"s:12_Concurrency20AsyncFlatMapSequenceV","text":"AsyncFlatMapSequence","kind":"typeIdentifier"},{"text":"<","kind":"text"},{"text":"Self","kind":"typeIdentifier"},{"text":", ","kind":"text"},{"text":"SegmentOfResult","kind":"typeIdentifier"},{"text":">","kind":"text"}],"kind":"symbol","title":"flatMap(_:)"},"doc://Afluent/documentation/Afluent/AsyncSequences/RetryAfterFlatMapping/sink(receiveCompletion:receiveOutput:)":{"fragments":[{"kind":"keyword","text":"func"},{"text":" ","kind":"text"},{"kind":"identifier","text":"sink"},{"kind":"text","text":"("},{"text":"receiveCompletion","kind":"externalParam"},{"text":": ((","kind":"text"},{"preciseIdentifier":"s:7Afluent14AsyncSequencesO","text":"AsyncSequences","kind":"typeIdentifier"},{"kind":"text","text":"."},{"kind":"typeIdentifier","preciseIdentifier":"s:7Afluent14AsyncSequencesO10CompletionO","text":"Completion"},{"kind":"text","text":"<"},{"preciseIdentifier":"s:s5ErrorP","text":"Error","kind":"typeIdentifier"},{"text":">) ","kind":"text"},{"kind":"keyword","text":"async"},{"kind":"text","text":" -> "},{"preciseIdentifier":"s:s4Voida","kind":"typeIdentifier","text":"Void"},{"text":")?, ","kind":"text"},{"text":"receiveOutput","kind":"externalParam"},{"text":": ((","kind":"text"},{"text":"Self","kind":"typeIdentifier"},{"text":".","kind":"text"},{"text":"Element","kind":"typeIdentifier"},{"kind":"text","text":") "},{"kind":"keyword","text":"async"},{"kind":"text","text":" "},{"kind":"keyword","text":"throws"},{"kind":"text","text":" -> "},{"text":"Void","kind":"typeIdentifier","preciseIdentifier":"s:s4Voida"},{"kind":"text","text":")?) -> "},{"text":"AnyCancellable","preciseIdentifier":"s:7Afluent14AnyCancellableC","kind":"typeIdentifier"}],"title":"sink(receiveCompletion:receiveOutput:)","url":"\/documentation\/afluent\/asyncsequences\/retryafterflatmapping\/sink(receivecompletion:receiveoutput:)","kind":"symbol","abstract":[{"type":"text","text":"Executes the current async sequence and returns an AnyCancellable token to cancel the subscription."}],"role":"symbol","identifier":"doc:\/\/Afluent\/documentation\/Afluent\/AsyncSequences\/RetryAfterFlatMapping\/sink(receiveCompletion:receiveOutput:)","conformance":{"constraints":[{"type":"codeVoice","code":"Self"},{"type":"text","text":" conforms to "},{"type":"codeVoice","code":"Sendable"},{"type":"text","text":"."}],"availabilityPrefix":[{"type":"text","text":"Available when"}],"conformancePrefix":[{"text":"Conforms when","type":"text"}]},"type":"topic"},"doc://Afluent/documentation/Afluent/AsyncSequences/RetryAfterFlatMapping/dropFirst(_:)":{"url":"\/documentation\/afluent\/asyncsequences\/retryafterflatmapping\/dropfirst(_:)","kind":"symbol","title":"dropFirst(_:)","identifier":"doc:\/\/Afluent\/documentation\/Afluent\/AsyncSequences\/RetryAfterFlatMapping\/dropFirst(_:)","fragments":[{"text":"func","kind":"keyword"},{"kind":"text","text":" "},{"text":"dropFirst","kind":"identifier"},{"text":"(","kind":"text"},{"kind":"typeIdentifier","preciseIdentifier":"s:Si","text":"Int"},{"text":") -> ","kind":"text"},{"text":"AsyncDropFirstSequence","kind":"typeIdentifier","preciseIdentifier":"s:12_Concurrency22AsyncDropFirstSequenceV"},{"kind":"text","text":"<"},{"text":"Self","kind":"typeIdentifier"},{"text":">","kind":"text"}],"abstract":[],"role":"symbol","type":"topic"},"doc://Afluent/documentation/Afluent/AsyncSequences/RetryAfterFlatMapping/catch(_:)":{"type":"topic","kind":"symbol","identifier":"doc:\/\/Afluent\/documentation\/Afluent\/AsyncSequences\/RetryAfterFlatMapping\/catch(_:)","role":"symbol","fragments":[{"text":"func","kind":"keyword"},{"kind":"text","text":" "},{"text":"`catch`","kind":"identifier"},{"kind":"text","text":"<"},{"kind":"genericParameter","text":"D"},{"kind":"text","text":">(("},{"preciseIdentifier":"s:s5ErrorP","text":"Error","kind":"typeIdentifier"},{"kind":"text","text":") "},{"text":"async","kind":"keyword"},{"text":" -> ","kind":"text"},{"kind":"typeIdentifier","text":"D"},{"text":") -> ","kind":"text"},{"kind":"typeIdentifier","text":"AsyncSequences","preciseIdentifier":"s:7Afluent14AsyncSequencesO"},{"text":".","kind":"text"},{"text":"Catch","kind":"typeIdentifier","preciseIdentifier":"s:7Afluent14AsyncSequencesO5CatchV"},{"text":"<","kind":"text"},{"kind":"typeIdentifier","text":"Self"},{"text":", ","kind":"text"},{"kind":"typeIdentifier","text":"D"},{"text":">","kind":"text"}],"abstract":[{"type":"text","text":"Catches any errors emitted by the upstream "},{"type":"codeVoice","code":"AsyncSequence"},{"text":" and handles them using the provided closure.","type":"text"}],"conformance":{"availabilityPrefix":[{"text":"Available when","type":"text"}],"conformancePrefix":[{"text":"Conforms when","type":"text"}],"constraints":[{"type":"codeVoice","code":"Self"},{"type":"text","text":" conforms to "},{"code":"Sendable","type":"codeVoice"},{"type":"text","text":"."}]},"url":"\/documentation\/afluent\/asyncsequences\/retryafterflatmapping\/catch(_:)","title":"catch(_:)"},"doc://Afluent/documentation/Afluent/AsyncSequences/RetryAfterFlatMapping/flatMap(maxSubscriptions:_:)":{"identifier":"doc:\/\/Afluent\/documentation\/Afluent\/AsyncSequences\/RetryAfterFlatMapping\/flatMap(maxSubscriptions:_:)","type":"topic","kind":"symbol","title":"flatMap(maxSubscriptions:_:)","role":"symbol","abstract":[],"url":"\/documentation\/afluent\/asyncsequences\/retryafterflatmapping\/flatmap(maxsubscriptions:_:)","fragments":[{"text":"func","kind":"keyword"},{"kind":"text","text":" "},{"text":"flatMap","kind":"identifier"},{"text":"<","kind":"text"},{"text":"SegmentOfResult","kind":"genericParameter"},{"kind":"text","text":">("},{"kind":"externalParam","text":"maxSubscriptions"},{"text":": ","kind":"text"},{"text":"SubscriptionDemand","kind":"typeIdentifier","preciseIdentifier":"s:7Afluent18SubscriptionDemandO"},{"text":", (","kind":"text"},{"text":"Self","kind":"typeIdentifier"},{"kind":"text","text":"."},{"text":"Element","kind":"typeIdentifier"},{"text":") ","kind":"text"},{"text":"async","kind":"keyword"},{"kind":"text","text":" "},{"text":"throws","kind":"keyword"},{"kind":"text","text":" -> "},{"text":"SegmentOfResult","kind":"typeIdentifier"},{"kind":"text","text":") -> "},{"text":"AsyncSequences","kind":"typeIdentifier","preciseIdentifier":"s:7Afluent14AsyncSequencesO"},{"text":".","kind":"text"},{"kind":"typeIdentifier","preciseIdentifier":"s:7Afluent14AsyncSequencesO7FlatMapV","text":"FlatMap"},{"kind":"text","text":"<"},{"text":"Self","kind":"typeIdentifier"},{"text":", ","kind":"text"},{"text":"SegmentOfResult","kind":"typeIdentifier"},{"text":">","kind":"text"}]},"doc://Afluent/documentation/Afluent/AsyncSequences/RetryAfterFlatMapping/contains(where:)":{"abstract":[],"role":"symbol","fragments":[{"text":"func","kind":"keyword"},{"kind":"text","text":" "},{"text":"contains","kind":"identifier"},{"text":"(","kind":"text"},{"text":"where","kind":"externalParam"},{"text":": (","kind":"text"},{"kind":"typeIdentifier","text":"Self"},{"text":".","kind":"text"},{"text":"Element","kind":"typeIdentifier"},{"text":") ","kind":"text"},{"text":"async","kind":"keyword"},{"text":" ","kind":"text"},{"kind":"keyword","text":"throws"},{"kind":"text","text":" -> "},{"preciseIdentifier":"s:Sb","kind":"typeIdentifier","text":"Bool"},{"text":") ","kind":"text"},{"kind":"keyword","text":"async"},{"text":" ","kind":"text"},{"text":"rethrows","kind":"keyword"},{"text":" -> ","kind":"text"},{"kind":"typeIdentifier","preciseIdentifier":"s:Sb","text":"Bool"}],"kind":"symbol","url":"\/documentation\/afluent\/asyncsequences\/retryafterflatmapping\/contains(where:)","identifier":"doc:\/\/Afluent\/documentation\/Afluent\/AsyncSequences\/RetryAfterFlatMapping\/contains(where:)","title":"contains(where:)","type":"topic"},"doc://Afluent/documentation/Afluent/AsyncSequences/RetryAfterFlatMapping/discardOutput()":{"identifier":"doc:\/\/Afluent\/documentation\/Afluent\/AsyncSequences\/RetryAfterFlatMapping\/discardOutput()","conformance":{"conformancePrefix":[{"type":"text","text":"Conforms when"}],"availabilityPrefix":[{"text":"Available when","type":"text"}],"constraints":[{"code":"Self","type":"codeVoice"},{"type":"text","text":" conforms to "},{"type":"codeVoice","code":"Sendable"},{"text":".","type":"text"}]},"role":"symbol","fragments":[{"text":"func","kind":"keyword"},{"kind":"text","text":" "},{"text":"discardOutput","kind":"identifier"},{"kind":"text","text":"() -> "},{"kind":"typeIdentifier","preciseIdentifier":"s:12_Concurrency16AsyncMapSequenceV","text":"AsyncMapSequence"},{"kind":"text","text":"<"},{"text":"Self","kind":"typeIdentifier"},{"text":", ","kind":"text"},{"kind":"typeIdentifier","preciseIdentifier":"s:s4Voida","text":"Void"},{"text":">","kind":"text"}],"type":"topic","title":"discardOutput()","kind":"symbol","abstract":[{"type":"text","text":"Discards the output values from the upstream "},{"code":"AsyncSequence","type":"codeVoice"},{"text":".","type":"text"}],"url":"\/documentation\/afluent\/asyncsequences\/retryafterflatmapping\/discardoutput()"},"doc://Afluent/documentation/Afluent/AsyncSequences/RetryAfterFlatMapping/handleEvents(receiveMakeIterator:receiveNext:receiveOutput:receiveError:receiveComplete:receiveCancel:)":{"type":"topic","abstract":[{"text":"Adds side-effects to the receiving events of the upstream ","type":"text"},{"type":"codeVoice","code":"AsyncSequence"},{"text":".","type":"text"}],"conformance":{"availabilityPrefix":[{"type":"text","text":"Available when"}],"conformancePrefix":[{"text":"Conforms when","type":"text"}],"constraints":[{"code":"Self","type":"codeVoice"},{"type":"text","text":" conforms to "},{"type":"codeVoice","code":"Sendable"},{"type":"text","text":"."}]},"kind":"symbol","role":"symbol","identifier":"doc:\/\/Afluent\/documentation\/Afluent\/AsyncSequences\/RetryAfterFlatMapping\/handleEvents(receiveMakeIterator:receiveNext:receiveOutput:receiveError:receiveComplete:receiveCancel:)","title":"handleEvents(receiveMakeIterator:receiveNext:receiveOutput:receiveError:receiveComplete:receiveCancel:)","url":"\/documentation\/afluent\/asyncsequences\/retryafterflatmapping\/handleevents(receivemakeiterator:receivenext:receiveoutput:receiveerror:receivecomplete:receivecancel:)","fragments":[{"text":"func","kind":"keyword"},{"text":" ","kind":"text"},{"kind":"identifier","text":"handleEvents"},{"text":"(","kind":"text"},{"kind":"externalParam","text":"receiveMakeIterator"},{"kind":"text","text":": (() -> "},{"text":"Void","kind":"typeIdentifier","preciseIdentifier":"s:s4Voida"},{"text":")?, ","kind":"text"},{"text":"receiveNext","kind":"externalParam"},{"text":": (() ","kind":"text"},{"kind":"keyword","text":"async"},{"kind":"text","text":" "},{"text":"throws","kind":"keyword"},{"text":" -> ","kind":"text"},{"preciseIdentifier":"s:s4Voida","kind":"typeIdentifier","text":"Void"},{"text":")?, ","kind":"text"},{"text":"receiveOutput","kind":"externalParam"},{"kind":"text","text":": (("},{"kind":"typeIdentifier","text":"Self"},{"kind":"text","text":"."},{"kind":"typeIdentifier","text":"Element"},{"kind":"text","text":") "},{"text":"async","kind":"keyword"},{"text":" ","kind":"text"},{"text":"throws","kind":"keyword"},{"kind":"text","text":" -> "},{"kind":"typeIdentifier","text":"Void","preciseIdentifier":"s:s4Voida"},{"kind":"text","text":")?, "},{"kind":"externalParam","text":"receiveError"},{"text":": ((","kind":"text"},{"kind":"typeIdentifier","preciseIdentifier":"s:s5ErrorP","text":"Error"},{"text":") ","kind":"text"},{"text":"async","kind":"keyword"},{"kind":"text","text":" "},{"kind":"keyword","text":"throws"},{"text":" -> ","kind":"text"},{"kind":"typeIdentifier","preciseIdentifier":"s:s4Voida","text":"Void"},{"kind":"text","text":")?, "},{"kind":"externalParam","text":"receiveComplete"},{"kind":"text","text":": (() "},{"text":"async","kind":"keyword"},{"text":" ","kind":"text"},{"text":"throws","kind":"keyword"},{"kind":"text","text":" -> "},{"text":"Void","preciseIdentifier":"s:s4Voida","kind":"typeIdentifier"},{"text":")?, ","kind":"text"},{"text":"receiveCancel","kind":"externalParam"},{"text":": (() ","kind":"text"},{"kind":"keyword","text":"async"},{"kind":"text","text":" "},{"kind":"keyword","text":"throws"},{"text":" -> ","kind":"text"},{"text":"Void","preciseIdentifier":"s:s4Voida","kind":"typeIdentifier"},{"kind":"text","text":")?) -> "},{"text":"AsyncSequences","kind":"typeIdentifier","preciseIdentifier":"s:7Afluent14AsyncSequencesO"},{"text":".","kind":"text"},{"preciseIdentifier":"s:7Afluent14AsyncSequencesO12HandleEventsV","text":"HandleEvents","kind":"typeIdentifier"},{"kind":"text","text":"<"},{"text":"Self","kind":"typeIdentifier"},{"text":">","kind":"text"}]},"doc://Afluent/documentation/Afluent/AsyncSequences/RetryAfterFlatMapping/map(_:)-9uds6":{"title":"map(_:)","abstract":[],"fragments":[{"kind":"keyword","text":"func"},{"text":" ","kind":"text"},{"text":"map","kind":"identifier"},{"text":"<","kind":"text"},{"text":"Transformed","kind":"genericParameter"},{"text":">((","kind":"text"},{"text":"Self","kind":"typeIdentifier"},{"kind":"text","text":"."},{"text":"Element","kind":"typeIdentifier"},{"text":") ","kind":"text"},{"text":"async","kind":"keyword"},{"kind":"text","text":" -> "},{"kind":"typeIdentifier","text":"Transformed"},{"kind":"text","text":") -> "},{"preciseIdentifier":"s:12_Concurrency16AsyncMapSequenceV","text":"AsyncMapSequence","kind":"typeIdentifier"},{"kind":"text","text":"<"},{"kind":"typeIdentifier","text":"Self"},{"kind":"text","text":", "},{"kind":"typeIdentifier","text":"Transformed"},{"kind":"text","text":">"}],"type":"topic","url":"\/documentation\/afluent\/asyncsequences\/retryafterflatmapping\/map(_:)-9uds6","identifier":"doc:\/\/Afluent\/documentation\/Afluent\/AsyncSequences\/RetryAfterFlatMapping\/map(_:)-9uds6","role":"symbol","kind":"symbol"},"doc://Afluent/documentation/Afluent/AsyncSequences/RetryAfterFlatMapping":{"abstract":[],"identifier":"doc:\/\/Afluent\/documentation\/Afluent\/AsyncSequences\/RetryAfterFlatMapping","navigatorTitle":[{"kind":"identifier","text":"RetryAfterFlatMapping"}],"fragments":[{"kind":"keyword","text":"class"},{"text":" ","kind":"text"},{"text":"RetryAfterFlatMapping","kind":"identifier"}],"kind":"symbol","url":"\/documentation\/afluent\/asyncsequences\/retryafterflatmapping","title":"AsyncSequences.RetryAfterFlatMapping","role":"symbol","type":"topic"},"doc://Afluent/documentation/Afluent/AsyncSequences/RetryAfterFlatMapping/characters":{"abstract":[],"identifier":"doc:\/\/Afluent\/documentation\/Afluent\/AsyncSequences\/RetryAfterFlatMapping\/characters","kind":"symbol","title":"characters","url":"\/documentation\/afluent\/asyncsequences\/retryafterflatmapping\/characters","role":"symbol","conformance":{"constraints":[{"type":"codeVoice","code":"Element"},{"type":"text","text":" is "},{"code":"UInt8","type":"codeVoice"},{"type":"text","text":"."}],"conformancePrefix":[{"text":"Conforms when","type":"text"}],"availabilityPrefix":[{"text":"Available when","type":"text"}]},"type":"topic","fragments":[{"text":"var","kind":"keyword"},{"kind":"text","text":" "},{"kind":"identifier","text":"characters"},{"text":": ","kind":"text"},{"kind":"typeIdentifier","preciseIdentifier":"s:10Foundation22AsyncCharacterSequenceV","text":"AsyncCharacterSequence"},{"text":"<","kind":"text"},{"text":"Self","kind":"typeIdentifier"},{"kind":"text","text":">"}]},"doc://Afluent/documentation/Afluent/AsyncSequences/RetryAfterFlatMapping/breakpoint(receiveOutput:receiveError:)":{"title":"breakpoint(receiveOutput:receiveError:)","identifier":"doc:\/\/Afluent\/documentation\/Afluent\/AsyncSequences\/RetryAfterFlatMapping\/breakpoint(receiveOutput:receiveError:)","role":"symbol","type":"topic","fragments":[{"kind":"keyword","text":"func"},{"kind":"text","text":" "},{"kind":"identifier","text":"breakpoint"},{"text":"(","kind":"text"},{"text":"receiveOutput","kind":"externalParam"},{"text":": ((","kind":"text"},{"kind":"typeIdentifier","text":"Self"},{"kind":"text","text":"."},{"text":"Element","kind":"typeIdentifier"},{"text":") ","kind":"text"},{"kind":"keyword","text":"async"},{"text":" ","kind":"text"},{"text":"throws","kind":"keyword"},{"text":" -> ","kind":"text"},{"text":"Bool","kind":"typeIdentifier","preciseIdentifier":"s:Sb"},{"text":")?, ","kind":"text"},{"text":"receiveError","kind":"externalParam"},{"text":": ((","kind":"text"},{"kind":"typeIdentifier","preciseIdentifier":"s:s5ErrorP","text":"Error"},{"text":") ","kind":"text"},{"kind":"keyword","text":"async"},{"kind":"text","text":" "},{"text":"throws","kind":"keyword"},{"text":" -> ","kind":"text"},{"kind":"typeIdentifier","text":"Bool","preciseIdentifier":"s:Sb"},{"text":")?) -> ","kind":"text"},{"kind":"typeIdentifier","text":"AsyncSequences","preciseIdentifier":"s:7Afluent14AsyncSequencesO"},{"text":".","kind":"text"},{"preciseIdentifier":"s:7Afluent14AsyncSequencesO12HandleEventsV","text":"HandleEvents","kind":"typeIdentifier"},{"text":"<","kind":"text"},{"text":"Self","kind":"typeIdentifier"},{"text":">","kind":"text"}],"kind":"symbol","abstract":[{"type":"text","text":"Introduces a breakpoint into the async sequence."}],"url":"\/documentation\/afluent\/asyncsequences\/retryafterflatmapping\/breakpoint(receiveoutput:receiveerror:)","conformance":{"availabilityPrefix":[{"type":"text","text":"Available when"}],"conformancePrefix":[{"type":"text","text":"Conforms when"}],"constraints":[{"code":"Self","type":"codeVoice"},{"type":"text","text":" conforms to "},{"type":"codeVoice","code":"Sendable"},{"text":".","type":"text"}]}},"doc://Afluent/documentation/Afluent/AsyncSequences/RetryAfterFlatMapping/retry(_:_:)":{"type":"topic","abstract":[{"text":"Retries the upstream ","type":"text"},{"code":"AsyncSequence","type":"codeVoice"},{"type":"text","text":" up to a specified number of times while applying a transformation on error."}],"kind":"symbol","url":"\/documentation\/afluent\/asyncsequences\/retryafterflatmapping\/retry(_:_:)","identifier":"doc:\/\/Afluent\/documentation\/Afluent\/AsyncSequences\/RetryAfterFlatMapping\/retry(_:_:)","title":"retry(_:_:)","fragments":[{"kind":"keyword","text":"func"},{"text":" ","kind":"text"},{"kind":"identifier","text":"retry"},{"text":"<","kind":"text"},{"text":"D","kind":"genericParameter"},{"text":">(","kind":"text"},{"text":"UInt","kind":"typeIdentifier","preciseIdentifier":"s:Su"},{"text":", (","kind":"text"},{"text":"Error","kind":"typeIdentifier","preciseIdentifier":"s:s5ErrorP"},{"text":") ","kind":"text"},{"text":"async","kind":"keyword"},{"kind":"text","text":" "},{"text":"throws","kind":"keyword"},{"text":" -> ","kind":"text"},{"text":"D","kind":"typeIdentifier"},{"text":") -> ","kind":"text"},{"text":"AsyncSequences","preciseIdentifier":"s:7Afluent14AsyncSequencesO","kind":"typeIdentifier"},{"kind":"text","text":"."},{"kind":"typeIdentifier","preciseIdentifier":"s:7Afluent14AsyncSequencesO21RetryAfterFlatMappingC","text":"RetryAfterFlatMapping"},{"kind":"text","text":"<"},{"text":"Self","kind":"typeIdentifier"},{"text":", ","kind":"text"},{"text":"D","kind":"typeIdentifier"},{"text":">","kind":"text"}],"conformance":{"availabilityPrefix":[{"text":"Available when","type":"text"}],"conformancePrefix":[{"text":"Conforms when","type":"text"}],"constraints":[{"code":"Self","type":"codeVoice"},{"text":" conforms to ","type":"text"},{"type":"codeVoice","code":"Sendable"},{"text":".","type":"text"}]},"role":"symbol"},"doc://Afluent/documentation/Afluent/AsyncSequences/RetryAfterFlatMapping/throttle(for:clock:latest:)":{"conformance":{"conformancePrefix":[{"type":"text","text":"Conforms when"}],"availabilityPrefix":[{"text":"Available when","type":"text"}],"constraints":[{"type":"codeVoice","code":"Self"},{"text":" conforms to ","type":"text"},{"type":"codeVoice","code":"Sendable"},{"type":"text","text":" and "},{"code":"Element","type":"codeVoice"},{"type":"text","text":" conforms to "},{"type":"codeVoice","code":"Sendable"},{"type":"text","text":"."}]},"identifier":"doc:\/\/Afluent\/documentation\/Afluent\/AsyncSequences\/RetryAfterFlatMapping\/throttle(for:clock:latest:)","abstract":[{"text":"Emits either the first or latest element received during a specified amount of time.","type":"text"}],"role":"symbol","url":"\/documentation\/afluent\/asyncsequences\/retryafterflatmapping\/throttle(for:clock:latest:)","type":"topic","fragments":[{"kind":"keyword","text":"func"},{"kind":"text","text":" "},{"text":"throttle","kind":"identifier"},{"kind":"text","text":"<"},{"kind":"genericParameter","text":"C"},{"kind":"text","text":">("},{"kind":"externalParam","text":"for"},{"kind":"text","text":": "},{"kind":"typeIdentifier","text":"C"},{"kind":"text","text":"."},{"kind":"typeIdentifier","text":"Duration"},{"text":", ","kind":"text"},{"kind":"externalParam","text":"clock"},{"kind":"text","text":": "},{"text":"C","kind":"typeIdentifier"},{"text":", ","kind":"text"},{"kind":"externalParam","text":"latest"},{"kind":"text","text":": "},{"kind":"typeIdentifier","text":"Bool","preciseIdentifier":"s:Sb"},{"kind":"text","text":") -> "},{"preciseIdentifier":"s:7Afluent14AsyncSequencesO","text":"AsyncSequences","kind":"typeIdentifier"},{"text":".","kind":"text"},{"text":"Throttle","preciseIdentifier":"s:7Afluent14AsyncSequencesO8ThrottleV","kind":"typeIdentifier"},{"text":"<","kind":"text"},{"text":"Self","kind":"typeIdentifier"},{"kind":"text","text":", "},{"text":"C","kind":"typeIdentifier"},{"text":">","kind":"text"}],"title":"throttle(for:clock:latest:)","kind":"symbol"},"doc://Afluent/documentation/Afluent/AsyncSequences/RetryAfterFlatMapping/first()":{"title":"first()","abstract":[{"type":"text","text":"Returns the first element of the sequence"}],"fragments":[{"kind":"keyword","text":"func"},{"text":" ","kind":"text"},{"text":"first","kind":"identifier"},{"kind":"text","text":"() "},{"kind":"keyword","text":"async"},{"kind":"text","text":" "},{"text":"rethrows","kind":"keyword"},{"text":" -> ","kind":"text"},{"text":"Self","kind":"typeIdentifier"},{"kind":"text","text":"."},{"text":"Element","kind":"typeIdentifier"},{"text":"?","kind":"text"}],"identifier":"doc:\/\/Afluent\/documentation\/Afluent\/AsyncSequences\/RetryAfterFlatMapping\/first()","kind":"symbol","role":"symbol","conformance":{"constraints":[{"code":"Element","type":"codeVoice"},{"text":" conforms to ","type":"text"},{"code":"Sendable","type":"codeVoice"},{"text":".","type":"text"}],"conformancePrefix":[{"text":"Conforms when","type":"text"}],"availabilityPrefix":[{"text":"Available when","type":"text"}]},"url":"\/documentation\/afluent\/asyncsequences\/retryafterflatmapping\/first()","type":"topic"},"doc://Afluent/documentation/Afluent/AsyncSequences/RetryAfterFlatMapping/groupBy(keySelector:)":{"title":"groupBy(keySelector:)","kind":"symbol","url":"\/documentation\/afluent\/asyncsequences\/retryafterflatmapping\/groupby(keyselector:)","role":"symbol","fragments":[{"text":"func","kind":"keyword"},{"kind":"text","text":" "},{"text":"groupBy","kind":"identifier"},{"text":"<","kind":"text"},{"text":"Key","kind":"genericParameter"},{"kind":"text","text":">("},{"kind":"externalParam","text":"keySelector"},{"kind":"text","text":": ("},{"text":"Self","kind":"typeIdentifier"},{"kind":"text","text":"."},{"text":"Element","kind":"typeIdentifier"},{"kind":"text","text":") "},{"text":"async","kind":"keyword"},{"kind":"text","text":" -> "},{"kind":"typeIdentifier","text":"Key"},{"kind":"text","text":") -> "},{"preciseIdentifier":"s:7Afluent14AsyncSequencesO","text":"AsyncSequences","kind":"typeIdentifier"},{"kind":"text","text":"."},{"preciseIdentifier":"s:7Afluent14AsyncSequencesO7GroupByV","kind":"typeIdentifier","text":"GroupBy"},{"kind":"text","text":"<"},{"text":"Self","kind":"typeIdentifier"},{"kind":"text","text":", "},{"kind":"typeIdentifier","text":"Key"},{"text":">","kind":"text"}],"conformance":{"conformancePrefix":[{"type":"text","text":"Conforms when"}],"availabilityPrefix":[{"text":"Available when","type":"text"}],"constraints":[{"code":"Self","type":"codeVoice"},{"type":"text","text":" conforms to "},{"code":"Sendable","type":"codeVoice"},{"type":"text","text":" and "},{"code":"Element","type":"codeVoice"},{"type":"text","text":" conforms to "},{"type":"codeVoice","code":"Sendable"},{"type":"text","text":"."}]},"identifier":"doc:\/\/Afluent\/documentation\/Afluent\/AsyncSequences\/RetryAfterFlatMapping\/groupBy(keySelector:)","abstract":[],"type":"topic"},"doc://Afluent/documentation/Afluent/AsyncSequences/RetryAfterFlatMapping/prefix(_:)":{"abstract":[],"role":"symbol","fragments":[{"text":"func","kind":"keyword"},{"text":" ","kind":"text"},{"kind":"identifier","text":"prefix"},{"kind":"text","text":"("},{"kind":"typeIdentifier","preciseIdentifier":"s:Si","text":"Int"},{"kind":"text","text":") -> "},{"text":"AsyncPrefixSequence","preciseIdentifier":"s:12_Concurrency19AsyncPrefixSequenceV","kind":"typeIdentifier"},{"text":"<","kind":"text"},{"kind":"typeIdentifier","text":"Self"},{"kind":"text","text":">"}],"kind":"symbol","url":"\/documentation\/afluent\/asyncsequences\/retryafterflatmapping\/prefix(_:)","identifier":"doc:\/\/Afluent\/documentation\/Afluent\/AsyncSequences\/RetryAfterFlatMapping\/prefix(_:)","title":"prefix(_:)","type":"topic"},"doc://Afluent/documentation/Afluent/AsyncSequences/RetryAfterFlatMapping/delay(for:tolerance:)":{"url":"\/documentation\/afluent\/asyncsequences\/retryafterflatmapping\/delay(for:tolerance:)","kind":"symbol","conformance":{"availabilityPrefix":[{"text":"Available when","type":"text"}],"conformancePrefix":[{"type":"text","text":"Conforms when"}],"constraints":[{"type":"codeVoice","code":"Self"},{"type":"text","text":" conforms to "},{"type":"codeVoice","code":"Sendable"},{"text":" and ","type":"text"},{"code":"Element","type":"codeVoice"},{"type":"text","text":" conforms to "},{"code":"Sendable","type":"codeVoice"},{"type":"text","text":"."}]},"title":"delay(for:tolerance:)","identifier":"doc:\/\/Afluent\/documentation\/Afluent\/AsyncSequences\/RetryAfterFlatMapping\/delay(for:tolerance:)","fragments":[{"text":"func","kind":"keyword"},{"kind":"text","text":" "},{"text":"delay","kind":"identifier"},{"text":"(","kind":"text"},{"kind":"externalParam","text":"for"},{"text":": ","kind":"text"},{"preciseIdentifier":"s:s8DurationV","text":"Duration","kind":"typeIdentifier"},{"kind":"text","text":", "},{"text":"tolerance","kind":"externalParam"},{"kind":"text","text":": "},{"text":"Duration","kind":"typeIdentifier","preciseIdentifier":"s:s8DurationV"},{"kind":"text","text":") -> "},{"kind":"typeIdentifier","text":"AsyncSequences","preciseIdentifier":"s:7Afluent14AsyncSequencesO"},{"text":".","kind":"text"},{"preciseIdentifier":"s:7Afluent14AsyncSequencesO5DelayV","kind":"typeIdentifier","text":"Delay"},{"kind":"text","text":"<"},{"text":"Self","kind":"typeIdentifier"},{"kind":"text","text":", "},{"text":"SuspendingClock","preciseIdentifier":"s:12_Concurrency15SuspendingClockV","kind":"typeIdentifier"},{"text":">","kind":"text"}],"abstract":[{"text":"Delays delivery of all output to the downstream receiver by a specified amount of time","type":"text"}],"role":"symbol","type":"topic"},"doc://Afluent/documentation/Afluent/AsyncSequences/RetryAfterFlatMapping/retry(_:on:)":{"url":"\/documentation\/afluent\/asyncsequences\/retryafterflatmapping\/retry(_:on:)","conformance":{"availabilityPrefix":[{"type":"text","text":"Available when"}],"constraints":[{"code":"Self","type":"codeVoice"},{"type":"text","text":" conforms to "},{"type":"codeVoice","code":"Sendable"},{"text":" and ","type":"text"},{"type":"codeVoice","code":"Element"},{"text":" conforms to ","type":"text"},{"type":"codeVoice","code":"Sendable"},{"type":"text","text":"."}],"conformancePrefix":[{"type":"text","text":"Conforms when"}]},"title":"retry(_:on:)","role":"symbol","identifier":"doc:\/\/Afluent\/documentation\/Afluent\/AsyncSequences\/RetryAfterFlatMapping\/retry(_:on:)","kind":"symbol","fragments":[{"text":"func","kind":"keyword"},{"kind":"text","text":" "},{"text":"retry","kind":"identifier"},{"text":"<","kind":"text"},{"kind":"genericParameter","text":"E"},{"kind":"text","text":">("},{"kind":"typeIdentifier","text":"UInt","preciseIdentifier":"s:Su"},{"kind":"text","text":", "},{"kind":"externalParam","text":"on"},{"text":": ","kind":"text"},{"kind":"typeIdentifier","text":"E"},{"kind":"text","text":") -> "},{"text":"AsyncSequences","kind":"typeIdentifier","preciseIdentifier":"s:7Afluent14AsyncSequencesO"},{"kind":"text","text":"."},{"kind":"typeIdentifier","preciseIdentifier":"s:7Afluent14AsyncSequencesO7RetryOnC","text":"RetryOn"},{"kind":"text","text":"<"},{"text":"Self","kind":"typeIdentifier"},{"kind":"text","text":", "},{"text":"E","kind":"typeIdentifier"},{"kind":"text","text":">"}],"type":"topic","abstract":[{"type":"text","text":"Retries the upstream "},{"type":"codeVoice","code":"AsyncSequence"},{"type":"text","text":" up to a specified number of times only when a specific error occurs."}]},"doc://Afluent/documentation/Afluent/AsyncSequences/RetryAfterFlatMapping/breakpointOnError()":{"identifier":"doc:\/\/Afluent\/documentation\/Afluent\/AsyncSequences\/RetryAfterFlatMapping\/breakpointOnError()","abstract":[{"text":"Introduces a breakpoint into the async sequence when an error occurs.","type":"text"}],"role":"symbol","conformance":{"constraints":[{"code":"Self","type":"codeVoice"},{"type":"text","text":" conforms to "},{"code":"Sendable","type":"codeVoice"},{"text":".","type":"text"}],"availabilityPrefix":[{"type":"text","text":"Available when"}],"conformancePrefix":[{"text":"Conforms when","type":"text"}]},"kind":"symbol","title":"breakpointOnError()","fragments":[{"kind":"keyword","text":"func"},{"kind":"text","text":" "},{"kind":"identifier","text":"breakpointOnError"},{"text":"() -> ","kind":"text"},{"kind":"typeIdentifier","text":"AsyncSequences","preciseIdentifier":"s:7Afluent14AsyncSequencesO"},{"text":".","kind":"text"},{"preciseIdentifier":"s:7Afluent14AsyncSequencesO12HandleEventsV","text":"HandleEvents","kind":"typeIdentifier"},{"kind":"text","text":"<"},{"text":"Self","kind":"typeIdentifier"},{"kind":"text","text":">"}],"type":"topic","url":"\/documentation\/afluent\/asyncsequences\/retryafterflatmapping\/breakpointonerror()"}}}